Workbook

Sheet Plano de Contas
A1: CONTA | B1: S | C1: D E N O M I N A C A O | D1: Natureza | E1: Classificação | F1: Grupo | G1: CP x LP | H1: Caracteres | I1: cod | J1: Grupo conta | K1: Grupo Relatório | L1: Revisão Analítica | M1: Notas | N1: Detalhe
A2: 1 | B2: S | C2: ATIVO | D2: D | E2: =LEFT(A2,1) -> 1 | F2: Ativo | G2: - | H2: =LEN(A2) -> 1 | I2: =IF(H2=11,A2,"-") -> - | J2: =IF(H2<11,C2,IF(I2<>"-",C2,J1)) -> ATIVO | S2: =C2='Plano de Contas sem ponto'!C2 -> TRUE
A3: 1.1 | B3: S | C3: ATIVO CIRCULANTE | D3: D | E3: =LEFT(A3,1) -> 1 | F3: Ativo | G3: Curto Prazo | H3: =LEN(A3) -> 3 | I3: =IF(H3=11,A3,"-") -> - | J3: =IF(H3<11,C3,IF(I3<>"-",C3,J2)) -> ATIVO CIRCULANTE | S3: =C3='Plano de Contas sem ponto'!C3 -> TRUE
A4: 1.1.1 | B4: S | C4: DISPONIVEL | D4: D | E4: =LEFT(A4,1) -> 1 | F4: Ativo | G4: Curto Prazo | H4: =LEN(A4) -> 5 | I4: =IF(H4=11,A4,"-") -> - | J4: =IF(H4<11,C4,IF(I4<>"-",C4,J3)) -> DISPONIVEL | S4: =C4='Plano de Contas sem ponto'!C4 -> TRUE
A5: 1.1.1.01 | B5: S | C5: CAIXA | D5: D | E5: =LEFT(A5,1) -> 1 | F5: Ativo | G5: Curto Prazo | H5: =LEN(A5) -> 8 | I5: =IF(H5=11,A5,"-") -> - | J5: =IF(H5<11,C5,IF(I5<>"-",C5,J4)) -> CAIXA | S5: =C5='Plano de Contas sem ponto'!C5 -> TRUE
A6: 1.1.1.01.01 | B6: S | C6: FUNDOS FIXOS | D6: D | E6: =LEFT(A6,1) -> 1 | F6: Ativo | G6: Curto Prazo | H6: =LEN(A6) -> 11 | I6: =IF(H6=11,A6,"-") -> 1.1.1.01.01 | J6: =IF(H6<11,C6,IF(I6<>"-",C6,J5)) -> FUNDOS FIXOS | K6: Caixa e equivalentes de caixa | L6: Fundo fixo | S6: =C6='Plano de Contas sem ponto'!C6 -> TRUE
A7: 1.1.1.01.01.0001 | B7: A | C7: FUNDO FIXO - RIO | D7: D | E7: =LEFT(A7,1) -> 1 | F7: Ativo | G7: Curto Prazo | H7: =LEN(A7) -> 16 | I7: =IF(H7=11,A7,"-") -> - | J7: =IF(H7<11,C7,IF(I7<>"-",C7,J6)) -> FUNDOS FIXOS | K7: Caixa e equivalentes de caixa | L7: Fundo fixo | S7: =C7='Plano de Contas sem ponto'!C7 -> TRUE
A8: 1.1.1.01.01.0002 | B8: A | C8: FUNDO FIXO - BRASILIA | D8: D | E8: =LEFT(A8,1) -> 1 | F8: Ativo | G8: Curto Prazo | H8: =LEN(A8) -> 16 | I8: =IF(H8=11,A8,"-") -> - | J8: =IF(H8<11,C8,IF(I8<>"-",C8,J7)) -> FUNDOS FIXOS | K8: Caixa e equivalentes de caixa | L8: Fundo fixo | S8: =C8='Plano de Contas sem ponto'!C8 -> TRUE
A9: 1.1.1.01.01.0003 | B9: A | C9: FUNDO FIXO - FENAPREVI | D9: D | E9: =LEFT(A9,1) -> 1 | F9: Ativo | G9: Curto Prazo | H9: =LEN(A9) -> 16 | I9: =IF(H9=11,A9,"-") -> - | J9: =IF(H9<11,C9,IF(I9<>"-",C9,J8)) -> FUNDOS FIXOS | K9: Caixa e equivalentes de caixa | L9: Fundo fixo | S9: =C9='Plano de Contas sem ponto'!C9 -> TRUE
A10: 1.1.1.01.01.0004 | B10: A | C10: FUNDO FIXO - FENSEG | D10: D | E10: =LEFT(A10,1) -> 1 | F10: Ativo | G10: Curto Prazo | H10: =LEN(A10) -> 16 | I10: =IF(H10=11,A10,"-") -> - | J10: =IF(H10<11,C10,IF(I10<>"-",C10,J9)) -> FUNDOS FIXOS | K10: Caixa e equivalentes de caixa | L10: Fundo fixo | S10: =C10='Plano de Contas sem ponto'!C10 -> TRUE
A11: 1.1.1.01.01.0005 | B11: A | C11: FUNDO FIXO - FENASAÚDE | D11: D | E11: =LEFT(A11,1) -> 1 | F11: Ativo | G11: Curto Prazo | H11: =LEN(A11) -> 16 | I11: =IF(H11=11,A11,"-") -> - | J11: =IF(H11<11,C11,IF(I11<>"-",C11,J10)) -> FUNDOS FIXOS | K11: Caixa e equivalentes de caixa | L11: Fundo fixo | S11: =C11='Plano de Contas sem ponto'!C11 -> TRUE
A12: 1.1.1.01.01.0006 | B12: A | C12: FUNDO FIXO - FENACAP | D12: D | E12: =LEFT(A12,1) -> 1 | F12: Ativo | G12: Curto Prazo | H12: =LEN(A12) -> 16 | I12: =IF(H12=11,A12,"-") -> - | J12: =IF(H12<11,C12,IF(I12<>"-",C12,J11)) -> FUNDOS FIXOS | K12: Caixa e equivalentes de caixa | L12: Fundo fixo | S12: =C12='Plano de Contas sem ponto'!C12 -> TRUE
A13: 1.1.1.01.01.0007 | B13: A | C13: FUNDO FIXO - SINDICATO | D13: D | E13: =LEFT(A13,1) -> 1 | F13: Ativo | G13: Curto Prazo | H13: =LEN(A13) -> 16 | I13: =IF(H13=11,A13,"-") -> - | J13: =IF(H13<11,C13,IF(I13<>"-",C13,J12)) -> FUNDOS FIXOS | K13: Caixa e equivalentes de caixa | L13: Fundo fixo | S13: =C13='Plano de Contas sem ponto'!C13 -> TRUE
A14: 1.1.1.01.01.0008 | B14: A | C14: FUNDO FIXO - CNSIMO | D14: D | E14: =LEFT(A14,1) -> 1 | F14: Ativo | G14: Curto Prazo | H14: =LEN(A14) -> 16 | I14: =IF(H14=11,A14,"-") -> - | J14: =IF(H14<11,C14,IF(I14<>"-",C14,J13)) -> FUNDOS FIXOS | K14: Caixa e equivalentes de caixa | L14: Fundo fixo | S14: =C14='Plano de Contas sem ponto'!C14 -> TRUE
A15: 1.1.1.01.01.0009 | B15: A | C15: FUNDO FIXO - CNSEG | D15: D | E15: =LEFT(A15,1) -> 1 | F15: Ativo | G15: Curto Prazo | H15: =LEN(A15) -> 16 | I15: =IF(H15=11,A15,"-") -> - | J15: =IF(H15<11,C15,IF(I15<>"-",C15,J14)) -> FUNDOS FIXOS | K15: Caixa e equivalentes de caixa | L15: Fundo fixo | S15: =C15='Plano de Contas sem ponto'!C15 -> TRUE
A16: 1.1.1.01.01.0010 | B16: A | C16: FUNDO FIXO - CNSPAR | D16: D | E16: =LEFT(A16,1) -> 1 | F16: Ativo | G16: Curto Prazo | H16: =LEN(A16) -> 16 | I16: =IF(H16=11,A16,"-") -> - | J16: =IF(H16<11,C16,IF(I16<>"-",C16,J15)) -> FUNDOS FIXOS | K16: Caixa e equivalentes de caixa | L16: Fundo fixo | S16: =C16='Plano de Contas sem ponto'!C16 -> TRUE
A17: 1.1.1.02 | B17: S | C17: BANCOS | D17: D | E17: =LEFT(A17,1) -> 1 | F17: Ativo | G17: Curto Prazo | H17: =LEN(A17) -> 8 | I17: =IF(H17=11,A17,"-") -> - | J17: =IF(H17<11,C17,IF(I17<>"-",C17,J16)) -> BANCOS | K17: Caixa e equivalentes de caixa | S17: =C17='Plano de Contas sem ponto'!C17 -> TRUE
A18: 1.1.1.02.01 | B18: S | C18: BANCOS CONTA MOVIMENTO | D18: D | E18: =LEFT(A18,1) -> 1 | F18: Ativo | G18: Curto Prazo | H18: =LEN(A18) -> 11 | I18: =IF(H18=11,A18,"-") -> 1.1.1.02.01 | J18: =IF(H18<11,C18,IF(I18<>"-",C18,J17)) -> BANCOS CONTA MOVIMENTO | K18: Caixa e equivalentes de caixa | L18: Bancos conta movimento | S18: =C18='Plano de Contas sem ponto'!C18 -> TRUE
A19: 1.1.1.02.01.0001 | B19: A | C19: BCO ITAU S/A - 0477/32832 | D19: D | E19: =LEFT(A19,1) -> 1 | F19: Ativo | G19: Curto Prazo | H19: =LEN(A19) -> 16 | I19: =IF(H19=11,A19,"-") -> - | J19: =IF(H19<11,C19,IF(I19<>"-",C19,J18)) -> BANCOS CONTA MOVIMENTO | K19: Caixa e equivalentes de caixa | L19: Bancos conta movimento | S19: =C19='Plano de Contas sem ponto'!C19 -> TRUE
A20: 1.1.1.02.01.0002 | B20: A | C20: BCO ITAU S/A - 0477/34759 | D20: D | E20: =LEFT(A20,1) -> 1 | F20: Ativo | G20: Curto Prazo | H20: =LEN(A20) -> 16 | I20: =IF(H20=11,A20,"-") -> - | J20: =IF(H20<11,C20,IF(I20<>"-",C20,J19)) -> BANCOS CONTA MOVIMENTO | K20: Caixa e equivalentes de caixa | L20: Bancos conta movimento | S20: =C20='Plano de Contas sem ponto'!C20 -> TRUE
A21: 1.1.1.02.01.0003 | B21: A | C21: BCO CAIXA ECONOMICA - 0542/775715-0 | D21: D | E21: =LEFT(A21,1) -> 1 | F21: Ativo | G21: Curto Prazo | H21: =LEN(A21) -> 16 | I21: =IF(H21=11,A21,"-") -> - | J21: =IF(H21<11,C21,IF(I21<>"-",C21,J20)) -> BANCOS CONTA MOVIMENTO | K21: Caixa e equivalentes de caixa | L21: Bancos conta movimento | S21: =C21='Plano de Contas sem ponto'!C21 -> TRUE
A22: 1.1.1.02.01.0004 | B22: A | C22: BCO BRASIL S/A - 1769/410 | D22: D | E22: =LEFT(A22,1) -> 1 | F22: Ativo | G22: Curto Prazo | H22: =LEN(A22) -> 16 | I22: =IF(H22=11,A22,"-") -> - | J22: =IF(H22<11,C22,IF(I22<>"-",C22,J21)) -> BANCOS CONTA MOVIMENTO | K22: Caixa e equivalentes de caixa | L22: Bancos conta movimento | S22: =C22='Plano de Contas sem ponto'!C22 -> TRUE
A23: 1.1.1.02.01.0005 | B23: A | C23: BCO ITAU S/A - 0477/63974 | D23: D | E23: =LEFT(A23,1) -> 1 | F23: Ativo | G23: Curto Prazo | H23: =LEN(A23) -> 16 | I23: =IF(H23=11,A23,"-") -> - | J23: =IF(H23<11,C23,IF(I23<>"-",C23,J22)) -> BANCOS CONTA MOVIMENTO | K23: Caixa e equivalentes de caixa | L23: Bancos conta movimento | S23: =C23='Plano de Contas sem ponto'!C23 -> TRUE
A24: 1.1.1.02.01.0006 | B24: A | C24: BCO BRADESCO - 2373/41669 | D24: D | E24: =LEFT(A24,1) -> 1 | F24: Ativo | G24: Curto Prazo | H24: =LEN(A24) -> 16 | I24: =IF(H24=11,A24,"-") -> - | J24: =IF(H24<11,C24,IF(I24<>"-",C24,J23)) -> BANCOS CONTA MOVIMENTO | K24: Caixa e equivalentes de caixa | L24: Bancos conta movimento | S24: =C24='Plano de Contas sem ponto'!C24 -> TRUE
A25: 1.1.1.02.01.0007 | B25: A | C25: BCO BRADESCO - 2373/41818 | D25: D | E25: =LEFT(A25,1) -> 1 | F25: Ativo | G25: Curto Prazo | H25: =LEN(A25) -> 16 | I25: =IF(H25=11,A25,"-") -> - | J25: =IF(H25<11,C25,IF(I25<>"-",C25,J24)) -> BANCOS CONTA MOVIMENTO | K25: Caixa e equivalentes de caixa | L25: Bancos conta movimento | S25: =C25='Plano de Contas sem ponto'!C25 -> TRUE
A26: 1.1.1.02.01.0008 | B26: A | C26: BCO ALFA S/A 0004/31276-2 | D26: D | E26: =LEFT(A26,1) -> 1 | F26: Ativo | G26: Curto Prazo | H26: =LEN(A26) -> 16 | I26: =IF(H26=11,A26,"-") -> - | J26: =IF(H26<11,C26,IF(I26<>"-",C26,J25)) -> BANCOS CONTA MOVIMENTO | K26: Caixa e equivalentes de caixa | L26: Bancos conta movimento | S26: =C26='Plano de Contas sem ponto'!C26 -> TRUE
A27: 1.1.1.02.01.0009 | B27: A | C27: BCO BRASIL -1769/8188-4 | D27: D | E27: =LEFT(A27,1) -> 1 | F27: Ativo | G27: Curto Prazo | H27: =LEN(A27) -> 16 | I27: =IF(H27=11,A27,"-") -> - | J27: =IF(H27<11,C27,IF(I27<>"-",C27,J26)) -> BANCOS CONTA MOVIMENTO | K27: Caixa e equivalentes de caixa | L27: Bancos conta movimento | S27: =C27='Plano de Contas sem ponto'!C27 -> TRUE
A28: 1.1.1.02.01.0010 | B28: A | C28: BCO BRADESCO 1803/415754-0 GRA | D28: D | E28: =LEFT(A28,1) -> 1 | F28: Ativo | G28: Curto Prazo | H28: =LEN(A28) -> 16 | I28: =IF(H28=11,A28,"-") -> - | J28: =IF(H28<11,C28,IF(I28<>"-",C28,J27)) -> BANCOS CONTA MOVIMENTO | K28: Caixa e equivalentes de caixa | L28: Bancos conta movimento | S28: =C28='Plano de Contas sem ponto'!C28 -> TRUE
A29: 1.1.1.02.01.0011 | B29: A | C29: BCO ITAU S/A - 0477/87124-8 | D29: D | E29: =LEFT(A29,1) -> 1 | F29: Ativo | G29: Curto Prazo | H29: =LEN(A29) -> 16 | I29: =IF(H29=11,A29,"-") -> - | J29: =IF(H29<11,C29,IF(I29<>"-",C29,J28)) -> BANCOS CONTA MOVIMENTO | K29: Caixa e equivalentes de caixa | L29: Bancos conta movimento | S29: =C29='Plano de Contas sem ponto'!C29 -> TRUE
... A61: 1.1.1.02.01.0043 | B61: A | C61: BCO ITAU S/A - 0477/19735-4 - CNSPAR | D61: D | E61: =LEFT(A61,1) -> 1 | F61: Ativo | G61: Curto Prazo | H61: =LEN(A61) -> 16 | I61: =IF(H61=11,A61,"-") -> - | J61: =IF(H61<11,C61,IF(I61<>"-",C61,J60)) -> BANCOS CONTA MOVIMENTO | K61: Caixa e equivalentes de caixa | L61: Bancos conta movimento | S61: =C61='Plano de Contas sem ponto'!C61 -> TRUE
A62: 1.1.1.02.01.0044 | B62: A | C62: BCO BEPAY - BPP INSTITUIÇÕES DE PAGAMENTOS 0001/200040270-2 | D62: D | E62: =LEFT(A62,1) -> 1 | F62: Ativo | G62: Curto Prazo | H62: =LEN(A62) -> 16 | I62: =IF(H62=11,A62,"-") -> - | J62: =IF(H62<11,C62,IF(I62<>"-",C62,J59)) -> BANCOS CONTA MOVIMENTO | K62: Caixa e equivalentes de caixa | L62: Bancos conta movimento | S62: =C62='Plano de Contas sem ponto'!C62 -> TRUE
A63: 1.1.1.02.01.0045 | B63: A | C63: BCO IUGU - IUGU INSTITUIÇÕES DE PAGAMENTOS 0002/5392769-0 | D63: D | E63: =LEFT(A63,1) -> 1 | F63: Ativo | G63: Curto Prazo | H63: =LEN(A63) -> 16 | I63: =IF(H63=11,A63,"-") -> - | J63: =IF(H63<11,C63,IF(I63<>"-",C63,J60)) -> BANCOS CONTA MOVIMENTO | K63: Caixa e equivalentes de caixa | L63: Bancos conta movimento | S63: =C63='Plano de Contas sem ponto'!C63 -> TRUE
A64: 1.1.1.02.02 | B64: S | C64: INVESTIMENTOS | D64: D | E64: =LEFT(A64,1) -> 1 | F64: Ativo | G64: Curto Prazo | H64: =LEN(A64) -> 11 | I64: =IF(H64=11,A64,"-") -> 1.1.1.02.02 | J64: =IF(H64<11,C64,IF(I64<>"-",C64,J61)) -> INVESTIMENTOS | K64: Caixa e equivalentes de caixa | S64: =C64='Plano de Contas sem ponto'!C64 -> TRUE
A65: 1.1.1.02.02.0001 | B65: A | C65: INVESTIMENTOS - EQUIVALENTE DE CAIXA | D65: D | E65: =LEFT(A65,1) -> 1 | F65: Ativo | G65: Curto Prazo | H65: =LEN(A65) -> 16 | I65: =IF(H65=11,A65,"-") -> - | J65: =IF(H65<11,C65,IF(I65<>"-",C65,J64)) -> INVESTIMENTOS | K65: Caixa e equivalentes de caixa | L65: Bancos conta movimento | S65: =C65='Plano de Contas sem ponto'!C65 -> TRUE
A66: 1.1.1.03 | B66: S | C66: APLICACOES FINANCEIRAS | D66: D | E66: =LEFT(A66,1) -> 1 | F66: Ativo | G66: Curto Prazo | H66: =LEN(A66) -> 8 | I66: =IF(H66=11,A66,"-") -> - | J66: =IF(H66<11,C66,IF(I66<>"-",C66,J65)) -> APLICACOES FINANCEIRAS | K66: Caixa e equivalentes de caixa | S66: =C66='Plano de Contas sem ponto'!C66 -> TRUE
A67: 1.1.1.03.01 | B67: S | C67: TITULOS DE RENDA FIXA | D67: D | E67: =LEFT(A67,1) -> 1 | F67: Ativo | G67: Curto Prazo | H67: =LEN(A67) -> 11 | I67: =IF(H67=11,A67,"-") -> 1.1.1.03.01 | J67: =IF(H67<11,C67,IF(I67<>"-",C67,J66)) -> TITULOS DE RENDA FIXA | K67: Caixa e equivalentes de caixa | L67: Titulos de renda fixa | S67: =C67='Plano de Contas sem ponto'!C67 -> TRUE
A68: 1.1.1.03.01.0001 | B68: A | C68: CDB/CDI | D68: D | E68: =LEFT(A68,1) -> 1 | F68: Ativo | G68: Curto Prazo | H68: =LEN(A68) -> 16 | I68: =IF(H68=11,A68,"-") -> - | J68: =IF(H68<11,C68,IF(I68<>"-",C68,J67)) -> TITULOS DE RENDA FIXA | K68: Caixa e equivalentes de caixa | L68: Titulos de renda fixa | S68: =C68='Plano de Contas sem ponto'!C68 -> TRUE
A69: 1.1.1.03.02 | B69: S | C69: TITULOS RENDA VARIÁVEL | D69: D | E69: =LEFT(A69,1) -> 1 | F69: Ativo | G69: Curto Prazo | H69: =LEN(A69) -> 11 | I69: =IF(H69=11,A69,"-") -> 1.1.1.03.02 | J69: =IF(H69<11,C69,IF(I69<>"-",C69,J68)) -> TITULOS RENDA VARIÁVEL | K69: Caixa e equivalentes de caixa | L69: Titulos renda variável | S69: =C69='Plano de Contas sem ponto'!C69 -> TRUE
A70: 1.1.1.03.02.0001 | B70: A | C70: ACOES | D70: D | E70: =LEFT(A70,1) -> 1 | F70: Ativo | G70: Curto Prazo | H70: =LEN(A70) -> 16 | I70: =IF(H70=11,A70,"-") -> - | J70: =IF(H70<11,C70,IF(I70<>"-",C70,J69)) -> TITULOS RENDA VARIÁVEL | K70: Caixa e equivalentes de caixa | L70: Titulos renda variável | S70: =C70='Plano de Contas sem ponto'!C70 -> TRUE
A71: 1.1.1.03.03 | B71: S | C71: QUOTAS E FUNDOS DE INVESTIMENTOS | D71: D | E71: =LEFT(A71,1) -> 1 | F71: Ativo | G71: Curto Prazo | H71: =LEN(A71) -> 11 | I71: =IF(H71=11,A71,"-") -> 1.1.1.03.03 | J71: =IF(H71<11,C71,IF(I71<>"-",C71,J70)) -> QUOTAS E FUNDOS DE INVESTIMENTOS | K71: Caixa e equivalentes de caixa | L71: Quotas e fundos de investimentos | S71: =C71='Plano de Contas sem ponto'!C71 -> TRUE
A72: 1.1.1.03.03.0001 | B72: A | C72: QUOTAS E FUNDOS DE INVESTIMENTOS | D72: D | E72: =LEFT(A72,1) -> 1 | F72: Ativo | G72: Curto Prazo | H72: =LEN(A72) -> 16 | I72: =IF(H72=11,A72,"-") -> - | J72: =IF(H72<11,C72,IF(I72<>"-",C72,J71)) -> QUOTAS E FUNDOS DE INVESTIMENTOS | K72: Caixa e equivalentes de caixa | L72: Quotas e fundos de investimentos | S72: =C72='Plano de Contas sem ponto'!C72 -> TRUE
A73: 1.1.1.03.04 | B73: S | C73: OUTRAS APLICACOES | D73: D | E73: =LEFT(A73,1) -> 1 | F73: Ativo | G73: Curto Prazo | H73: =LEN(A73) -> 11 | I73: =IF(H73=11,A73,"-") -> 1.1.1.03.04 | J73: =IF(H73<11,C73,IF(I73<>"-",C73,J72)) -> OUTRAS APLICACOES | K73: Caixa e equivalentes de caixa | L73: Outras aplicacoes | S73: =C73='Plano de Contas sem ponto'!C73 -> TRUE
A74: 1.1.1.03.04.0001 | B74: A | C74: OUTRAS APLICACOES | D74: D | E74: =LEFT(A74,1) -> 1 | F74: Ativo | G74: Curto Prazo | H74: =LEN(A74) -> 16 | I74: =IF(H74=11,A74,"-") -> - | J74: =IF(H74<11,C74,IF(I74<>"-",C74,J73)) -> OUTRAS APLICACOES | K74: Caixa e equivalentes de caixa | L74: Outras aplicacoes | S74: =C74='Plano de Contas sem ponto'!C74 -> TRUE
A75: 1.1.2 | B75: S | C75: CONTAS A RECEBER | D75: D | E75: =LEFT(A75,1) -> 1 | F75: Ativo | G75: Curto Prazo | H75: =LEN(A75) -> 5 | I75: =IF(H75=11,A75,"-") -> - | J75: =IF(H75<11,C75,IF(I75<>"-",C75,J74)) -> CONTAS A RECEBER | K75: Contas a receber | L75: Contas a Receber | S75: =C75='Plano de Contas sem ponto'!C75 -> TRUE
A76: 1.1.2.01 | B76: S | C76: CONTAS A RECEBER | D76: D | E76: =LEFT(A76,1) -> 1 | F76: Ativo | G76: Curto Prazo | H76: =LEN(A76) -> 8 | I76: =IF(H76=11,A76,"-") -> - | J76: =IF(H76<11,C76,IF(I76<>"-",C76,J75)) -> CONTAS A RECEBER | K76: Contas a receber | L76: Contas a Receber | S76: =C76='Plano de Contas sem ponto'!C76 -> TRUE
A77: 1.1.2.01.01 | B77: S | C77: CONTAS A RECEBER | D77: D | E77: =LEFT(A77,1) -> 1 | F77: Ativo | G77: Curto Prazo | H77: =LEN(A77) -> 11 | I77: =IF(H77=11,A77,"-") -> 1.1.2.01.01 | J77: =IF(H77<11,C77,IF(I77<>"-",C77,J76)) -> CONTAS A RECEBER | K77: Contas a receber | L77: Contas a Receber | S77: =C77='Plano de Contas sem ponto'!C77 -> TRUE
A78: 1.1.2.01.01.0001 | B78: A | C78: CONTAS A RECEBER | D78: D | E78: =LEFT(A78,1) -> 1 | F78: Ativo | G78: Curto Prazo | H78: =LEN(A78) -> 16 | I78: =IF(H78=11,A78,"-") -> - | J78: =IF(H78<11,C78,IF(I78<>"-",C78,J77)) -> CONTAS A RECEBER | K78: Contas a receber | L78: Contas a Receber | S78: =C78='Plano de Contas sem ponto'!C78 -> TRUE
A79: 1.1.2.01.02 | B79: S | C79: CONTAS A RECEBER - OUTROS CLIENTES | D79: D | E79: =LEFT(A79,1) -> 1 | F79: Ativo | G79: Curto Prazo | H79: =LEN(A79) -> 11 | I79: =IF(H79=11,A79,"-") -> 1.1.2.01.02 | J79: =IF(H79<11,C79,IF(I79<>"-",C79,J78)) -> CONTAS A RECEBER - OUTROS CLIENTES | K79: Contas a receber | S79: =C79='Plano de Contas sem ponto'!C79 -> TRUE
A80: 1.1.2.01.02.0001 | B80: A | C80: CONTAS A RECEBER - OUTROS CLIENTES | D80: D | E80: =LEFT(A80,1) -> 1 | F80: Ativo | G80: Curto Prazo | H80: =LEN(A80) -> 16 | I80: =IF(H80=11,A80,"-") -> - | J80: =IF(H80<11,C80,IF(I80<>"-",C80,J79)) -> CONTAS A RECEBER - OUTROS CLIENTES | K80: Contas a receber | L80: Contas a Receber | S80: =C80='Plano de Contas sem ponto'!C80 -> TRUE
A81: 1.1.2.01.99 | B81: S | C81: PROVISAO CREDITO LIQUID. DUVIDOSA | D81: C | E81: =LEFT(A81,1) -> 1 | F81: Ativo | G81: Curto Prazo | H81: =LEN(A81) -> 11 | I81: =IF(H81=11,A81,"-") -> 1.1.2.01.99 | J81: =IF(H81<11,C81,IF(I81<>"-",C81,J80)) -> PROVISAO CREDITO LIQUID. DUVIDOSA | K81: Contas a receber | S81: =C81='Plano de Contas sem ponto'!C81 -> TRUE
A82: 1.1.2.01.99.0001 | B82: A | C82: PROVISAO CREDITO LIQUID. DUVIDOSA | D82: C | E82: =LEFT(A82,1) -> 1 | F82: Ativo | G82: Curto Prazo | H82: =LEN(A82) -> 16 | I82: =IF(H82=11,A82,"-") -> - | J82: =IF(H82<11,C82,IF(I82<>"-",C82,J81)) -> PROVISAO CREDITO LIQUID. DUVIDOSA | K82: Contas a receber | L82: Provisão p/ crédito liquidação duvidosa | S82: =C82='Plano de Contas sem ponto'!C82 -> TRUE
A83: 1.1.3 | B83: S | C83: CREDITOS A RECEBER | D83: D | E83: =LEFT(A83,1) -> 1 | F83: Ativo | G83: Curto Prazo | H83: =LEN(A83) -> 5 | I83: =IF(H83=11,A83,"-") -> - | J83: =IF(H83<11,C83,IF(I83<>"-",C83,J82)) -> CREDITOS A RECEBER | K83: Outros ativos | S83: =C83='Plano de Contas sem ponto'!C83 -> TRUE
A84: 1.1.3.01 | B84: S | C84: CREDITOS A RECEBER | D84: D | E84: =LEFT(A84,1) -> 1 | F84: Ativo | G84: Curto Prazo | H84: =LEN(A84) -> 8 | I84: =IF(H84=11,A84,"-") -> - | J84: =IF(H84<11,C84,IF(I84<>"-",C84,J83)) -> CREDITOS A RECEBER | K84: Outros ativos | S84: =C84='Plano de Contas sem ponto'!C84 -> TRUE
A85: 1.1.3.01.00 | B85: S | C85: FEDERACOES / SINDICATOS | D85: D | E85: =LEFT(A85,1) -> 1 | F85: Ativo | G85: Curto Prazo | H85: =LEN(A85) -> 11 | I85: =IF(H85=11,A85,"-") -> 1.1.3.01.00 | J85: =IF(H85<11,C85,IF(I85<>"-",C85,J84)) -> FEDERACOES / SINDICATOS | K85: Outros ativos | S85: =C85='Plano de Contas sem ponto'!C85 -> TRUE
A86: 1.1.3.01.00.0001 | B86: A | C86: CREDITOS A RECEBER | D86: D | E86: =LEFT(A86,1) -> 1 | F86: Ativo | G86: Curto Prazo | H86: =LEN(A86) -> 16 | I86: =IF(H86=11,A86,"-") -> - | J86: =IF(H86<11,C86,IF(I86<>"-",C86,J85)) -> FEDERACOES / SINDICATOS | K86: Outros ativos | S86: =C86='Plano de Contas sem ponto'!C86 -> TRUE
A87: 1.1.3.01.00.0002 | B87: A | C87: FENSEG | D87: D | E87: =LEFT(A87,1) -> 1 | F87: Ativo | G87: Curto Prazo | H87: =LEN(A87) -> 16 | I87: =IF(H87=11,A87,"-") -> - | J87: =IF(H87<11,C87,IF(I87<>"-",C87,J86)) -> FEDERACOES / SINDICATOS | K87: Outros ativos | S87: =C87='Plano de Contas sem ponto'!C87 -> TRUE
A88: 1.1.3.01.00.0003 | B88: A | C88: FENASAUDE | D88: D | E88: =LEFT(A88,1) -> 1 | F88: Ativo | G88: Curto Prazo | H88: =LEN(A88) -> 16 | I88: =IF(H88=11,A88,"-") -> - | J88: =IF(H88<11,C88,IF(I88<>"-",C88,J87)) -> FEDERACOES / SINDICATOS | K88: Outros ativos | S88: =C88='Plano de Contas sem ponto'!C88 -> TRUE
A89: 1.1.3.01.00.0004 | B89: A | C89: FENAPREVI | D89: D | E89: =LEFT(A89,1) -> 1 | F89: Ativo | G89: Curto Prazo | H89: =LEN(A89) -> 16 | I89: =IF(H89=11,A89,"-") -> - | J89: =IF(H89<11,C89,IF(I89<>"-",C89,J88)) -> FEDERACOES / SINDICATOS | K89: Outros ativos | S89: =C89='Plano de Contas sem ponto'!C89 -> TRUE
A90: 1.1.3.01.00.0005 | B90: A | C90: FENACAP | D90: D | E90: =LEFT(A90,1) -> 1 | F90: Ativo | G90: Curto Prazo | H90: =LEN(A90) -> 16 | I90: =IF(H90=11,A90,"-") -> - | J90: =IF(H90<11,C90,IF(I90<>"-",C90,J89)) -> FEDERACOES / SINDICATOS | K90: Outros ativos | S90: =C90='Plano de Contas sem ponto'!C90 -> TRUE
A91: 1.1.3.01.00.0006 | B91: A | C91: SINDICATO DAS SEGURADORAS | D91: D | E91: =LEFT(A91,1) -> 1 | F91: Ativo | G91: Curto Prazo | H91: =LEN(A91) -> 16 | I91: =IF(H91=11,A91,"-") -> - | J91: =IF(H91<11,C91,IF(I91<>"-",C91,J90)) -> FEDERACOES / SINDICATOS | K91: Outros ativos | S91: =C91='Plano de Contas sem ponto'!C91 -> TRUE
A92: 1.1.3.01.00.0007 | B92: A | C92: CNSIMO | D92: D | E92: =LEFT(A92,1) -> 1 | F92: Ativo | G92: Curto Prazo | H92: =LEN(A92) -> 16 | I92: =IF(H92=11,A92,"-") -> - | J92: =IF(H92<11,C92,IF(I92<>"-",C92,J91)) -> FEDERACOES / SINDICATOS | K92: Outros ativos | S92: =C92='Plano de Contas sem ponto'!C92 -> TRUE
A93: 1.1.3.01.00.0008 | B93: A | C93: CNSEG | D93: D | E93: =LEFT(A93,1) -> 1 | F93: Ativo | G93: Curto Prazo | H93: =LEN(A93) -> 16 | I93: =IF(H93=11,A93,"-") -> - | J93: =IF(H93<11,C93,IF(I93<>"-",C93,J92)) -> FEDERACOES / SINDICATOS | K93: Outros ativos | S93: =C93='Plano de Contas sem ponto'!C93 -> TRUE
A94: 1.1.3.01.01 | B94: S | C94: CREDITOS A RECEBER - OUTROS | D94: D | E94: =LEFT(A94,1) -> 1 | F94: Ativo | G94: Curto Prazo | H94: =LEN(A94) -> 11 | I94: =IF(H94=11,A94,"-") -> 1.1.3.01.01 | J94: =IF(H94<11,C94,IF(I94<>"-",C94,J93)) -> CREDITOS A RECEBER - OUTROS | K94: Outros ativos | S94: =C94='Plano de Contas sem ponto'!C94 -> TRUE
... A101: 1.1.3.01.01.0007 | B101: A | C101: COMPRA DE MOEDA ESTRANGEIRA - DOLAR | D101: D | E101: =LEFT(A101,1) -> 1 | F101: Ativo | G101: Curto Prazo | H101: =LEN(A101) -> 16 | I101: =IF(H101=11,A101,"-") -> - | J101: =IF(H101<11,C101,IF(I101<>"-",C101,J100)) -> CREDITOS A RECEBER - OUTROS | K101: Outros ativos | S101: =C101='Plano de Contas sem ponto'!C101 -> TRUE
A102: 1.1.3.01.01.0008 | B102: A | C102: COMPRA DE MOEDA ESTRANGEIRA - EURO | D102: D | E102: =LEFT(A102,1) -> 1 | F102: Ativo | G102: Curto Prazo | H102: =LEN(A102) -> 16 | I102: =IF(H102=11,A102,"-") -> - | J102: =IF(H102<11,C102,IF(I102<>"-",C102,J100)) -> CREDITOS A RECEBER - OUTROS | K102: Outros ativos | S102: =C102='Plano de Contas sem ponto'!C102 -> TRUE
A103: 1.1.3.01.01.0009 | B103: A | C103: BEPAY/IUGU- BPP/IUGU CARTÃO DE CREDITO | D103: D | E103: =LEFT(A103,1) -> 1 | F103: Ativo | G103: Curto Prazo | H103: =LEN(A103) -> 16 | I103: =IF(H103=11,A103,"-") -> - | J103: =IF(H103<11,C103,IF(I103<>"-",C103,J101)) -> CREDITOS A RECEBER - OUTROS | K103: Outros ativos | S103: =C103='Plano de Contas sem ponto'!C103 -> TRUE
A104: 1.1.3.01.01.0010 | B104: A | C104: PAYPAL- CARTÃO DE CRÉDITO | D104: D | E104: =LEFT(A104,1) -> 1 | F104: Ativo | G104: Curto Prazo | H104: =LEN(A104) -> 16 | I104: =IF(H104=11,A104,"-") -> - | J104: =IF(H104<11,C104,IF(I104<>"-",C104,J101)) -> CREDITOS A RECEBER - OUTROS | K104: Outros ativos | S104: =C104='Plano de Contas sem ponto'!C104 -> TRUE
A105: 1.1.3.01.02 | B105: S | C105: RATEIOS A RECUPERAR | D105: D | E105: =LEFT(A105,1) -> 1 | F105: Ativo | G105: Curto Prazo | H105: =LEN(A105) -> 11 | I105: =IF(H105=11,A105,"-") -> 1.1.3.01.02 | J105: =IF(H105<11,C105,IF(I105<>"-",C105,J104)) -> RATEIOS A RECUPERAR | K105: Outros ativos | S105: =C105='Plano de Contas sem ponto'!C105 -> TRUE
A106: 1.1.3.01.02.0001 | B106: A | C106: RATEIOS A RECUPERAR | D106: D | E106: =LEFT(A106,1) -> 1 | F106: Ativo | G106: Curto Prazo | H106: =LEN(A106) -> 16 | I106: =IF(H106=11,A106,"-") -> - | J106: =IF(H106<11,C106,IF(I106<>"-",C106,J105)) -> RATEIOS A RECUPERAR | K106: Outros ativos | S106: =C106='Plano de Contas sem ponto'!C106 -> TRUE
A107: 1.1.3.01.03 | B107: S | C107: ADIANTAMENTOS A TERCEIROS | D107: D | E107: =LEFT(A107,1) -> 1 | F107: Ativo | G107: Curto Prazo | H107: =LEN(A107) -> 11 | I107: =IF(H107=11,A107,"-") -> 1.1.3.01.03 | J107: =IF(H107<11,C107,IF(I107<>"-",C107,J106)) -> ADIANTAMENTOS A TERCEIROS | K107: Outros ativos | S107: =C107='Plano de Contas sem ponto'!C107 -> TRUE
A108: 1.1.3.01.03.0001 | B108: A | C108: ADIANTAMENTOS A TERCEIROS | D108: D | E108: =LEFT(A108,1) -> 1 | F108: Ativo | G108: Curto Prazo | H108: =LEN(A108) -> 16 | I108: =IF(H108=11,A108,"-") -> - | J108: =IF(H108<11,C108,IF(I108<>"-",C108,J107)) -> ADIANTAMENTOS A TERCEIROS | K108: Outros ativos | S108: =C108='Plano de Contas sem ponto'!C108 -> TRUE
A109: 1.1.3.01.04 | B109: S | C109: VALORES A RECUPERAR | D109: D | E109: =LEFT(A109,1) -> 1 | F109: Ativo | G109: Curto Prazo | H109: =LEN(A109) -> 11 | I109: =IF(H109=11,A109,"-") -> 1.1.3.01.04 | J109: =IF(H109<11,C109,IF(I109<>"-",C109,J108)) -> VALORES A RECUPERAR | K109: Outros ativos | S109: =C109='Plano de Contas sem ponto'!C109 -> TRUE
A110: 1.1.3.01.04.0001 | B110: A | C110: VALORES A RECUPERAR | D110: D | E110: =LEFT(A110,1) -> 1 | F110: Ativo | G110: Curto Prazo | H110: =LEN(A110) -> 16 | I110: =IF(H110=11,A110,"-") -> - | J110: =IF(H110<11,C110,IF(I110<>"-",C110,J109)) -> VALORES A RECUPERAR | K110: Outros ativos | S110: =C110='Plano de Contas sem ponto'!C110 -> TRUE
A111: 1.1.3.01.04.0002 | B111: A | C111: VALORES A RECUPERAR - GRAVAMES | D111: D | E111: =LEFT(A111,1) -> 1 | F111: Ativo | G111: Curto Prazo | H111: =LEN(A111) -> 16 | I111: =IF(H111=11,A111,"-") -> - | J111: =IF(H111<11,C111,IF(I111<>"-",C111,J110)) -> VALORES A RECUPERAR | K111: Outros ativos | S111: =C111='Plano de Contas sem ponto'!C111 -> TRUE
A112: 1.1.3.01.05 | B112: S | C112: ADIANTAMENTOS A FUNCIONARIOS | D112: D | E112: =LEFT(A112,1) -> 1 | F112: Ativo | G112: Curto Prazo | H112: =LEN(A112) -> 11 | I112: =IF(H112=11,A112,"-") -> 1.1.3.01.05 | J112: =IF(H112<11,C112,IF(I112<>"-",C112,J111)) -> ADIANTAMENTOS A FUNCIONARIOS | K112: Outros ativos | S112: =C112='Plano de Contas sem ponto'!C112 -> TRUE
A113: 1.1.3.01.05.0001 | B113: A | C113: ADIANTAMENTO SALARIAL | D113: D | E113: =LEFT(A113,1) -> 1 | F113: Ativo | G113: Curto Prazo | H113: =LEN(A113) -> 16 | I113: =IF(H113=11,A113,"-") -> - | J113: =IF(H113<11,C113,IF(I113<>"-",C113,J112)) -> ADIANTAMENTOS A FUNCIONARIOS | K113: Outros ativos | S113: =C113='Plano de Contas sem ponto'!C113 -> TRUE
A114: 1.1.3.01.05.0002 | B114: A | C114: ADIANTAMENTO DE FERIAS | D114: D | E114: =LEFT(A114,1) -> 1 | F114: Ativo | G114: Curto Prazo | H114: =LEN(A114) -> 16 | I114: =IF(H114=11,A114,"-") -> - | J114: =IF(H114<11,C114,IF(I114<>"-",C114,J113)) -> ADIANTAMENTOS A FUNCIONARIOS | K114: Outros ativos | S114: =C114='Plano de Contas sem ponto'!C114 -> TRUE
A115: 1.1.3.01.05.0003 | B115: A | C115: ANTECIPACAO DO 13 SALARIO | D115: D | E115: =LEFT(A115,1) -> 1 | F115: Ativo | G115: Curto Prazo | H115: =LEN(A115) -> 16 | I115: =IF(H115=11,A115,"-") -> - | J115: =IF(H115<11,C115,IF(I115<>"-",C115,J114)) -> ADIANTAMENTOS A FUNCIONARIOS | K115: Outros ativos | S115: =C115='Plano de Contas sem ponto'!C115 -> TRUE
A116: 1.1.3.01.05.0004 | B116: A | C116: ADIANTAMENTO DE GRATIFICACAO | D116: D | E116: =LEFT(A116,1) -> 1 | F116: Ativo | G116: Curto Prazo | H116: =LEN(A116) -> 16 | I116: =IF(H116=11,A116,"-") -> - | J116: =IF(H116<11,C116,IF(I116<>"-",C116,J115)) -> ADIANTAMENTOS A FUNCIONARIOS | K116: Outros ativos | S116: =C116='Plano de Contas sem ponto'!C116 -> TRUE
... A136: 1.1.3.01.09.0002 | B136: A | C136: ANTECIPACAO COFINS S/ INSCRICAO DE EVENTOS | D136: D | E136: =LEFT(A136,1) -> 1 | F136: Ativo | G136: Curto Prazo | H136: =LEN(A136) -> 16 | I136: =IF(H136=11,A136,"-") -> - | J136: =IF(H136<11,C136,IF(I136<>"-",C136,J135)) -> ANTECIPACAO DE IMPOSTOS S/ INSCRICAO DE EVENTOS | K136: Outros ativos | S136: =C136='Plano de Contas sem ponto'!C136 -> TRUE
A137: 1.1.3.01.09.0003 | B137: A | C137: ANTECIPACAO ISS S/ PATROCÍNIO DE EVENTOS | D137: D | E137: =LEFT(A137,1) -> 1 | F137: Ativo | G137: Curto Prazo | H137: =LEN(A137) -> 16 | I137: =IF(H137=11,A137,"-") -> - | J137: =IF(H137<11,C137,IF(I137<>"-",C137,J136)) -> ANTECIPACAO DE IMPOSTOS S/ INSCRICAO DE EVENTOS | K137: Outros ativos | S137: FALSE
A138: 1.1.3.01.09.0004 | B138: A | C138: ANTECIPACAO COFINS S/ PATROCÍNIO DE EVENTOANTECIPACAO COFINS S/ PATROCÍNIO DE EVENTOS | D138: D | E138: =LEFT(A138,1) -> 1 | F138: Ativo | G138: Curto Prazo | H138: =LEN(A138) -> 16 | I138: =IF(H138=11,A138,"-") -> - | J138: =IF(H138<11,C138,IF(I138<>"-",C138,J137)) -> ANTECIPACAO DE IMPOSTOS S/ INSCRICAO DE EVENTOS | K138: Outros ativos | S138: FALSE
A139: 1.1.4 | B139: S | C139: PARTES RELACIONADAS | D139: D | E139: =LEFT(A139,1) -> 1 | F139: Ativo | G139: Curto Prazo | H139: =LEN(A139) -> 5 | I139: =IF(H139=11,A139,"-") -> - | J139: =IF(H139<11,C139,IF(I139<>"-",C139,J133)) -> PARTES RELACIONADAS | K139: Transações com partes relacionadas (Ativo) | L139: Transações com partes relacionadas (Ativo) | S139: =C139='Plano de Contas sem ponto'!C139 -> TRUE
A140: 1.1.4.01 | B140: S | C140: PARTES RELACIONADAS | D140: D | E140: =LEFT(A140,1) -> 1 | F140: Ativo | G140: Curto Prazo | H140: =LEN(A140) -> 8 | I140: =IF(H140=11,A140,"-") -> - | J140: =IF(H140<11,C140,IF(I140<>"-",C140,J139)) -> PARTES RELACIONADAS | K140: Transações com partes relacionadas (Ativo) | L140: Transações com partes relacionadas (Ativo) | S140: =C140='Plano de Contas sem ponto'!C140 -> TRUE
A141: 1.1.4.01.01 | B141: S | C141: PARTES RELACIONADAS | D141: D | E141: =LEFT(A141,1) -> 1 | F141: Ativo | G141: Curto Prazo | H141: =LEN(A141) -> 11 | I141: =IF(H141=11,A141,"-") -> 1.1.4.01.01 | J141: =IF(H141<11,C141,IF(I141<>"-",C141,J140)) -> PARTES RELACIONADAS | K141: Transações com partes relacionadas (Ativo) | L141: Transações com partes relacionadas (Ativo) | S141: =C141='Plano de Contas sem ponto'!C141 -> TRUE
A142: 1.1.4.01.01.0001 | B142: A | C142: PARTES RELACIONADAS | D142: D | E142: =LEFT(A142,1) -> 1 | F142: Ativo | G142: Curto Prazo | H142: =LEN(A142) -> 16 | I142: =IF(H142=11,A142,"-") -> - | J142: =IF(H142<11,C142,IF(I142<>"-",C142,J141)) -> PARTES RELACIONADAS | K142: Transações com partes relacionadas (Ativo) | L142: Transações com partes relacionadas (Ativo) | S142: =C142='Plano de Contas sem ponto'!C142 -> TRUE
A143: 1.1.5 | B143: S | C143: ALMOXARIFADO | D143: D | E143: =LEFT(A143,1) -> 1 | F143: Ativo | G143: Curto Prazo | H143: =LEN(A143) -> 5 | I143: =IF(H143=11,A143,"-") -> - | J143: =IF(H143<11,C143,IF(I143<>"-",C143,J142)) -> ALMOXARIFADO | K143: Outros ativos | S143: =C143='Plano de Contas sem ponto'!C143 -> TRUE
A144: 1.1.5.01 | B144: S | C144: ALMOXARIFADO | D144: D | E144: =LEFT(A144,1) -> 1 | F144: Ativo | G144: Curto Prazo | H144: =LEN(A144) -> 8 | I144: =IF(H144=11,A144,"-") -> - | J144: =IF(H144<11,C144,IF(I144<>"-",C144,J143)) -> ALMOXARIFADO | K144: Outros ativos | S144: =C144='Plano de Contas sem ponto'!C144 -> TRUE
A145: 1.1.5.01.01 | B145: S | C145: MATERIAIS DIVERSOS | D145: D | E145: =LEFT(A145,1) -> 1 | F145: Ativo | G145: Curto Prazo | H145: =LEN(A145) -> 11 | I145: =IF(H145=11,A145,"-") -> 1.1.5.01.01 | J145: =IF(H145<11,C145,IF(I145<>"-",C145,J144)) -> MATERIAIS DIVERSOS | K145: Outros ativos | S145: =C145='Plano de Contas sem ponto'!C145 -> TRUE
A146: 1.1.5.01.01.0001 | B146: A | C146: MATERIAL DE ESCRITORIO | D146: D | E146: =LEFT(A146,1) -> 1 | F146: Ativo | G146: Curto Prazo | H146: =LEN(A146) -> 16 | I146: =IF(H146=11,A146,"-") -> - | J146: =IF(H146<11,C146,IF(I146<>"-",C146,J145)) -> MATERIAIS DIVERSOS | K146: Outros ativos | S146: =C146='Plano de Contas sem ponto'!C146 -> TRUE
A147: 1.1.5.01.01.0002 | B147: A | C147: MATERIAL SERVICOS/COPA | D147: D | E147: =LEFT(A147,1) -> 1 | F147: Ativo | G147: Curto Prazo | H147: =LEN(A147) -> 16 | I147: =IF(H147=11,A147,"-") -> - | J147: =IF(H147<11,C147,IF(I147<>"-",C147,J146)) -> MATERIAIS DIVERSOS | K147: Outros ativos | S147: =C147='Plano de Contas sem ponto'!C147 -> TRUE
A148: 1.1.5.01.01.0003 | B148: A | C148: MATERIAL DE LIMPEZA | D148: D | E148: =LEFT(A148,1) -> 1 | F148: Ativo | G148: Curto Prazo | H148: =LEN(A148) -> 16 | I148: =IF(H148=11,A148,"-") -> - | J148: =IF(H148<11,C148,IF(I148<>"-",C148,J147)) -> MATERIAIS DIVERSOS | K148: Outros ativos | S148: =C148='Plano de Contas sem ponto'!C148 -> TRUE
A149: 1.1.5.01.01.0004 | B149: A | C149: MATERIAL DE INFORMATICA | D149: D | E149: =LEFT(A149,1) -> 1 | F149: Ativo | G149: Curto Prazo | H149: =LEN(A149) -> 16 | I149: =IF(H149=11,A149,"-") -> - | J149: =IF(H149<11,C149,IF(I149<>"-",C149,J148)) -> MATERIAIS DIVERSOS | K149: Outros ativos | S149: =C149='Plano de Contas sem ponto'!C149 -> TRUE
A150: 1.1.5.01.01.0005 | B150: A | C150: MATERIAL DE MANUTENCAO | D150: D | E150: =LEFT(A150,1) -> 1 | F150: Ativo | G150: Curto Prazo | H150: =LEN(A150) -> 16 | I150: =IF(H150=11,A150,"-") -> - | J150: =IF(H150<11,C150,IF(I150<>"-",C150,J149)) -> MATERIAIS DIVERSOS | K150: Outros ativos | S150: =C150='Plano de Contas sem ponto'!C150 -> TRUE
A151: 1.1.5.01.01.0006 | B151: A | C151: MATERIAL DE EVENTOS | D151: D | E151: =LEFT(A151,1) -> 1 | F151: Ativo | G151: Curto Prazo | H151: =LEN(A151) -> 16 | I151: =IF(H151=11,A151,"-") -> - | J151: =IF(H151<11,C151,IF(I151<>"-",C151,J150)) -> MATERIAIS DIVERSOS | K151: Outros ativos | S151: =C151='Plano de Contas sem ponto'!C151 -> TRUE
A152: 1.1.6 | B152: S | C152: DESPESAS ANTECIPADAS | D152: D | E152: =LEFT(A152,1) -> 1 | F152: Ativo | G152: Curto Prazo | H152: =LEN(A152) -> 5 | I152: =IF(H152=11,A152,"-") -> - | J152: =IF(H152<11,C152,IF(I152<>"-",C152,J151)) -> DESPESAS ANTECIPADAS | K152: Outros ativos | S152: =C152='Plano de Contas sem ponto'!C152 -> TRUE
A153: 1.1.6.01 | B153: S | C153: DESPESAS ANTECIPADAS | D153: D | E153: =LEFT(A153,1) -> 1 | F153: Ativo | G153: Curto Prazo | H153: =LEN(A153) -> 8 | I153: =IF(H153=11,A153,"-") -> - | J153: =IF(H153<11,C153,IF(I153<>"-",C153,J152)) -> DESPESAS ANTECIPADAS | K153: Outros ativos | S153: =C153='Plano de Contas sem ponto'!C153 -> TRUE
A154: 1.1.6.01.01 | B154: S | C154: DESPESAS ADMINISTRATIVAS ANTECIPADAS | D154: D | E154: =LEFT(A154,1) -> 1 | F154: Ativo | G154: Curto Prazo | H154: =LEN(A154) -> 11 | I154: =IF(H154=11,A154,"-") -> 1.1.6.01.01 | J154: =IF(H154<11,C154,IF(I154<>"-",C154,J153)) -> DESPESAS ADMINISTRATIVAS ANTECIPADAS | K154: Outros ativos | S154: =C154='Plano de Contas sem ponto'!C154 -> TRUE
... A165: 1.2.1.01 | B165: S | C165: CREDITOS E VALORES | D165: D | E165: =LEFT(A165,1) -> 1 | F165: Ativo | G165: Longo Prazo | H165: =LEN(A165) -> 8 | I165: =IF(H165=11,A165,"-") -> - | J165: =IF(H165<11,C165,IF(I165<>"-",C165,J164)) -> CREDITOS E VALORES | K165: Outros ativos | S165: =C165='Plano de Contas sem ponto'!C165 -> TRUE
A166: 1.2.1.01.01 | B166: S | C166: DIREITOS CREDITORIOS | D166: D | E166: =LEFT(A166,1) -> 1 | F166: Ativo | G166: Longo Prazo | H166: =LEN(A166) -> 11 | I166: =IF(H166=11,A166,"-") -> 1.2.1.01.01 | J166: =IF(H166<11,C166,IF(I166<>"-",C166,J165)) -> DIREITOS CREDITORIOS | K166: Depósitos judiciais | L166: Depósitos judiciais | S166: =C166='Plano de Contas sem ponto'!C166 -> TRUE
...

Sheet Plano de Contas sem ponto
A1: CONTA | B1: S | C1: D E N O M I N A C A O | D1: Natureza | E1: Classificação | F1: Grupo | G1: CP x LP | H1: Caracteres | I1: cod | J1: Grupo conta | K1: Grupo Relatório | L1: Revisão Analítica | M1: Notas | N1: Detalhe
A2: 1 | B2: S | C2: ATIVO | D2: D | E2: 1 | F2: Ativo | G2: - | H2: 1 | I2: - | J2: ATIVO | S2: =C2='Plano de Contas'!C2 -> TRUE
A3: 11 | B3: S | C3: ATIVO CIRCULANTE | D3: D | E3: 1 | F3: Ativo | G3: Curto Prazo | H3: 3 | I3: - | J3: ATIVO CIRCULANTE | S3: =C3='Plano de Contas'!C3 -> TRUE
A4: 111 | B4: S | C4: DISPONIVEL | D4: D | E4: 1 | F4: Ativo | G4: Curto Prazo | H4: 5 | I4: - | J4: DISPONIVEL | S4: =C4='Plano de Contas'!C4 -> TRUE
A5: 11101 | B5: S | C5: CAIXA | D5: D | E5: 1 | F5: Ativo | G5: Curto Prazo | H5: 8 | I5: - | J5: CAIXA | S5: =C5='Plano de Contas'!C5 -> TRUE
A6: 1110101 | B6: S | C6: FUNDOS FIXOS | D6: D | E6: 1 | F6: Ativo | G6: Curto Prazo | H6: 11 | I6: 1.1.1.01.01 | J6: FUNDOS FIXOS | K6: Caixa e equivalentes de caixa | L6: Fundo fixo | S6: =C6='Plano de Contas'!C6 -> TRUE
A7: 11101010001 | B7: A | C7: FUNDO FIXO - RIO | D7: D | E7: 1 | F7: Ativo | G7: Curto Prazo | H7: 16 | I7: - | J7: FUNDOS FIXOS | K7: Caixa e equivalentes de caixa | L7: Fundo fixo | S7: =C7='Plano de Contas'!C7 -> TRUE
A8: 11101010002 | B8: A | C8: FUNDO FIXO - BRASILIA | D8: D | E8: 1 | F8: Ativo | G8: Curto Prazo | H8: 16 | I8: - | J8: FUNDOS FIXOS | K8: Caixa e equivalentes de caixa | L8: Fundo fixo | S8: =C8='Plano de Contas'!C8 -> TRUE
A9: 11101010003 | B9: A | C9: FUNDO FIXO - FENAPREVI | D9: D | E9: 1 | F9: Ativo | G9: Curto Prazo | H9: 16 | I9: - | J9: FUNDOS FIXOS | K9: Caixa e equivalentes de caixa | L9: Fundo fixo | S9: =C9='Plano de Contas'!C9 -> TRUE
A10: 11101010004 | B10: A | C10: FUNDO FIXO - FENSEG | D10: D | E10: 1 | F10: Ativo | G10: Curto Prazo | H10: 16 | I10: - | J10: FUNDOS FIXOS | K10: Caixa e equivalentes de caixa | L10: Fundo fixo | S10: =C10='Plano de Contas'!C10 -> TRUE
A11: 11101010005 | B11: A | C11: FUNDO FIXO - FENASAÚDE | D11: D | E11: 1 | F11: Ativo | G11: Curto Prazo | H11: 16 | I11: - | J11: FUNDOS FIXOS | K11: Caixa e equivalentes de caixa | L11: Fundo fixo | S11: =C11='Plano de Contas'!C11 -> TRUE
A12: 11101010006 | B12: A | C12: FUNDO FIXO - FENACAP | D12: D | E12: 1 | F12: Ativo | G12: Curto Prazo | H12: 16 | I12: - | J12: FUNDOS FIXOS | K12: Caixa e equivalentes de caixa | L12: Fundo fixo | S12: =C12='Plano de Contas'!C12 -> TRUE
A13: 11101010007 | B13: A | C13: FUNDO FIXO - SINDICATO | D13: D | E13: 1 | F13: Ativo | G13: Curto Prazo | H13: 16 | I13: - | J13: FUNDOS FIXOS | K13: Caixa e equivalentes de caixa | L13: Fundo fixo | S13: =C13='Plano de Contas'!C13 -> TRUE
A14: 11101010008 | B14: A | C14: FUNDO FIXO - CNSIMO | D14: D | E14: 1 | F14: Ativo | G14: Curto Prazo | H14: 16 | I14: - | J14: FUNDOS FIXOS | K14: Caixa e equivalentes de caixa | L14: Fundo fixo | S14: =C14='Plano de Contas'!C14 -> TRUE
A15: 11101010009 | B15: A | C15: FUNDO FIXO - CNSEG | D15: D | E15: 1 | F15: Ativo | G15: Curto Prazo | H15: 16 | I15: - | J15: FUNDOS FIXOS | K15: Caixa e equivalentes de caixa | L15: Fundo fixo | S15: =C15='Plano de Contas'!C15 -> TRUE
A16: 11101010010 | B16: A | C16: FUNDO FIXO - CNSPAR | D16: D | E16: 1 | F16: Ativo | G16: Curto Prazo | H16: 16 | I16: - | J16: FUNDOS FIXOS | K16: Caixa e equivalentes de caixa | L16: Fundo fixo | S16: =C16='Plano de Contas'!C16 -> TRUE
A17: 11102 | B17: S | C17: BANCOS | D17: D | E17: 1 | F17: Ativo | G17: Curto Prazo | H17: 8 | I17: - | J17: BANCOS | K17: Caixa e equivalentes de caixa | S17: =C17='Plano de Contas'!C17 -> TRUE
A18: 1110201 | B18: S | C18: BANCOS CONTA MOVIMENTO | D18: D | E18: 1 | F18: Ativo | G18: Curto Prazo | H18: 11 | I18: 1.1.1.02.01 | J18: BANCOS CONTA MOVIMENTO | K18: Caixa e equivalentes de caixa | L18: Bancos conta movimento | S18: =C18='Plano de Contas'!C18 -> TRUE
A19: 11102010001 | B19: A | C19: BCO ITAU S/A - 0477/32832 | D19: D | E19: 1 | F19: Ativo | G19: Curto Prazo | H19: 16 | I19: - | J19: BANCOS CONTA MOVIMENTO | K19: Caixa e equivalentes de caixa | L19: Bancos conta movimento | S19: =C19='Plano de Contas'!C19 -> TRUE
A20: 11102010002 | B20: A | C20: BCO ITAU S/A - 0477/34759 | D20: D | E20: 1 | F20: Ativo | G20: Curto Prazo | H20: 16 | I20: - | J20: BANCOS CONTA MOVIMENTO | K20: Caixa e equivalentes de caixa | L20: Bancos conta movimento | S20: =C20='Plano de Contas'!C20 -> TRUE
A21: 11102010003 | B21: A | C21: BCO CAIXA ECONOMICA - 0542/775715-0 | D21: D | E21: 1 | F21: Ativo | G21: Curto Prazo | H21: 16 | I21: - | J21: BANCOS CONTA MOVIMENTO | K21: Caixa e equivalentes de caixa | L21: Bancos conta movimento | S21: =C21='Plano de Contas'!C21 -> TRUE
A22: 11102010004 | B22: A | C22: BCO BRASIL S/A - 1769/410 | D22: D | E22: 1 | F22: Ativo | G22: Curto Prazo | H22: 16 | I22: - | J22: BANCOS CONTA MOVIMENTO | K22: Caixa e equivalentes de caixa | L22: Bancos conta movimento | S22: =C22='Plano de Contas'!C22 -> TRUE
A23: 11102010005 | B23: A | C23: BCO ITAU S/A - 0477/63974 | D23: D | E23: 1 | F23: Ativo | G23: Curto Prazo | H23: 16 | I23: - | J23: BANCOS CONTA MOVIMENTO | K23: Caixa e equivalentes de caixa | L23: Bancos conta movimento | S23: =C23='Plano de Contas'!C23 -> TRUE
A24: 11102010006 | B24: A | C24: BCO BRADESCO - 2373/41669 | D24: D | E24: 1 | F24: Ativo | G24: Curto Prazo | H24: 16 | I24: - | J24: BANCOS CONTA MOVIMENTO | K24: Caixa e equivalentes de caixa | L24: Bancos conta movimento | S24: =C24='Plano de Contas'!C24 -> TRUE
A25: 11102010007 | B25: A | C25: BCO BRADESCO - 2373/41818 | D25: D | E25: 1 | F25: Ativo | G25: Curto Prazo | H25: 16 | I25: - | J25: BANCOS CONTA MOVIMENTO | K25: Caixa e equivalentes de caixa | L25: Bancos conta movimento | S25: =C25='Plano de Contas'!C25 -> TRUE
A26: 11102010008 | B26: A | C26: BCO ALFA S/A 0004/31276-2 | D26: D | E26: 1 | F26: Ativo | G26: Curto Prazo | H26: 16 | I26: - | J26: BANCOS CONTA MOVIMENTO | K26: Caixa e equivalentes de caixa | L26: Bancos conta movimento | S26: =C26='Plano de Contas'!C26 -> TRUE
A27: 11102010009 | B27: A | C27: BCO BRASIL -1769/8188-4 | D27: D | E27: 1 | F27: Ativo | G27: Curto Prazo | H27: 16 | I27: - | J27: BANCOS CONTA MOVIMENTO | K27: Caixa e equivalentes de caixa | L27: Bancos conta movimento | S27: =C27='Plano de Contas'!C27 -> TRUE
A28: 11102010010 | B28: A | C28: BCO BRADESCO 1803/415754-0 GRA | D28: D | E28: 1 | F28: Ativo | G28: Curto Prazo | H28: 16 | I28: - | J28: BANCOS CONTA MOVIMENTO | K28: Caixa e equivalentes de caixa | L28: Bancos conta movimento | S28: =C28='Plano de Contas'!C28 -> TRUE
A29: 11102010011 | B29: A | C29: BCO ITAU S/A - 0477/87124-8 | D29: D | E29: 1 | F29: Ativo | G29: Curto Prazo | H29: 16 | I29: - | J29: BANCOS CONTA MOVIMENTO | K29: Caixa e equivalentes de caixa | L29: Bancos conta movimento | S29: =C29='Plano de Contas'!C29 -> TRUE
... A61: 11102010043 | B61: A | C61: BCO ITAU S/A - 0477/19735-4 - CNSPAR | D61: D | E61: 1 | F61: Ativo | G61: Curto Prazo | H61: 16 | I61: - | J61: BANCOS CONTA MOVIMENTO | K61: Caixa e equivalentes de caixa | L61: Bancos conta movimento | S61: =C61='Plano de Contas'!C61 -> TRUE
A62: 11102010044 | B62: A | C62: BCO BEPAY - BPP INSTITUIÇÕES DE PAGAMENTOS 0001/200040270-2 | D62: D | E62: =LEFT(A62,1) -> 1 | F62: Ativo | G62: Curto Prazo | H62: =LEN(A62) -> 11 | I62: - | J62: =IF(H62<11,C62,IF(I62<>"-",C62,J59)) -> BANCOS CONTA MOVIMENTO | K62: Caixa e equivalentes de caixa | L62: Bancos conta movimento | S62: =C62='Plano de Contas'!C62 -> TRUE
A63: 11102010045 | B63: A | C63: BCO IUGU - IUGU INSTITUIÇÕES DE PAGAMENTOS 0002/5392769-0 | D63: D | E63: =LEFT(A63,1) -> 1 | F63: Ativo | G63: Curto Prazo | H63: =LEN(A63) -> 11 | I63: - | J63: =IF(H63<11,C63,IF(I63<>"-",C63,J60)) -> BANCOS CONTA MOVIMENTO | K63: Caixa e equivalentes de caixa | L63: Bancos conta movimento | S63: =C63='Plano de Contas'!C63 -> TRUE
A64: 1110202 | B64: S | C64: INVESTIMENTOS | D64: D | E64: 1 | F64: Ativo | G64: Curto Prazo | H64: 11 | I64: 1.1.1.02.02 | J64: INVESTIMENTOS | K64: Caixa e equivalentes de caixa | S64: =C64='Plano de Contas'!C64 -> TRUE
A65: 11102020001 | B65: A | C65: INVESTIMENTOS - EQUIVALENTE DE CAIXA | D65: D | E65: 1 | F65: Ativo | G65: Curto Prazo | H65: 16 | I65: - | J65: INVESTIMENTOS | K65: Caixa e equivalentes de caixa | L65: Bancos conta movimento | S65: =C65='Plano de Contas'!C65 -> TRUE
A66: 11103 | B66: S | C66: APLICACOES FINANCEIRAS | D66: D | E66: 1 | F66: Ativo | G66: Curto Prazo | H66: 8 | I66: - | J66: APLICACOES FINANCEIRAS | K66: Caixa e equivalentes de caixa | S66: =C66='Plano de Contas'!C66 -> TRUE
A67: 1110301 | B67: S | C67: TITULOS DE RENDA FIXA | D67: D | E67: 1 | F67: Ativo | G67: Curto Prazo | H67: 11 | I67: 1.1.1.03.01 | J67: TITULOS DE RENDA FIXA | K67: Caixa e equivalentes de caixa | L67: Titulos de renda fixa | S67: =C67='Plano de Contas'!C67 -> TRUE
A68: 11103010001 | B68: A | C68: CDB/CDI | D68: D | E68: 1 | F68: Ativo | G68: Curto Prazo | H68: 16 | I68: - | J68: TITULOS DE RENDA FIXA | K68: Caixa e equivalentes de caixa | L68: Titulos de renda fixa | S68: =C68='Plano de Contas'!C68 -> TRUE
A69: 1110302 | B69: S | C69: TITULOS RENDA VARIÁVEL | D69: D | E69: 1 | F69: Ativo | G69: Curto Prazo | H69: 11 | I69: 1.1.1.03.02 | J69: TITULOS RENDA VARIÁVEL | K69: Caixa e equivalentes de caixa | L69: Titulos renda variável | S69: =C69='Plano de Contas'!C69 -> TRUE
A70: 11103020001 | B70: A | C70: ACOES | D70: D | E70: 1 | F70: Ativo | G70: Curto Prazo | H70: 16 | I70: - | J70: TITULOS RENDA VARIÁVEL | K70: Caixa e equivalentes de caixa | L70: Titulos renda variável | S70: =C70='Plano de Contas'!C70 -> TRUE
A71: 1110303 | B71: S | C71: QUOTAS E FUNDOS DE INVESTIMENTOS | D71: D | E71: 1 | F71: Ativo | G71: Curto Prazo | H71: 11 | I71: 1.1.1.03.03 | J71: QUOTAS E FUNDOS DE INVESTIMENTOS | K71: Caixa e equivalentes de caixa | L71: Quotas e fundos de investimentos | S71: =C71='Plano de Contas'!C71 -> TRUE
A72: 11103030001 | B72: A | C72: QUOTAS E FUNDOS DE INVESTIMENTOS | D72: D | E72: 1 | F72: Ativo | G72: Curto Prazo | H72: 16 | I72: - | J72: QUOTAS E FUNDOS DE INVESTIMENTOS | K72: Caixa e equivalentes de caixa | L72: Quotas e fundos de investimentos | S72: =C72='Plano de Contas'!C72 -> TRUE
A73: 1110304 | B73: S | C73: OUTRAS APLICACOES | D73: D | E73: 1 | F73: Ativo | G73: Curto Prazo | H73: 11 | I73: 1.1.1.03.04 | J73: OUTRAS APLICACOES | K73: Caixa e equivalentes de caixa | L73: Outras aplicacoes | S73: =C73='Plano de Contas'!C73 -> TRUE
A74: 11103040001 | B74: A | C74: OUTRAS APLICACOES | D74: D | E74: 1 | F74: Ativo | G74: Curto Prazo | H74: 16 | I74: - | J74: OUTRAS APLICACOES | K74: Caixa e equivalentes de caixa | L74: Outras aplicacoes | S74: =C74='Plano de Contas'!C74 -> TRUE
A75: 112 | B75: S | C75: CONTAS A RECEBER | D75: D | E75: 1 | F75: Ativo | G75: Curto Prazo | H75: 5 | I75: - | J75: CONTAS A RECEBER | K75: Contas a receber | L75: Contas a Receber | S75: =C75='Plano de Contas'!C75 -> TRUE
A76: 11201 | B76: S | C76: CONTAS A RECEBER | D76: D | E76: 1 | F76: Ativo | G76: Curto Prazo | H76: 8 | I76: - | J76: CONTAS A RECEBER | K76: Contas a receber | L76: Contas a Receber | S76: =C76='Plano de Contas'!C76 -> TRUE
A77: 1120101 | B77: S | C77: CONTAS A RECEBER | D77: D | E77: 1 | F77: Ativo | G77: Curto Prazo | H77: 11 | I77: 1.1.2.01.01 | J77: CONTAS A RECEBER | K77: Contas a receber | L77: Contas a Receber | S77: =C77='Plano de Contas'!C77 -> TRUE
A78: 11201010001 | B78: A | C78: CONTAS A RECEBER | D78: D | E78: 1 | F78: Ativo | G78: Curto Prazo | H78: 16 | I78: - | J78: CONTAS A RECEBER | K78: Contas a receber | L78: Contas a Receber | S78: =C78='Plano de Contas'!C78 -> TRUE
A79: 1120102 | B79: S | C79: CONTAS A RECEBER - OUTROS CLIENTES | D79: D | E79: 1 | F79: Ativo | G79: Curto Prazo | H79: 11 | I79: 1.1.2.01.02 | J79: CONTAS A RECEBER - OUTROS CLIENTES | K79: Contas a receber | S79: =C79='Plano de Contas'!C79 -> TRUE
A80: 11201020001 | B80: A | C80: CONTAS A RECEBER - OUTROS CLIENTES | D80: D | E80: 1 | F80: Ativo | G80: Curto Prazo | H80: 16 | I80: - | J80: CONTAS A RECEBER - OUTROS CLIENTES | K80: Contas a receber | L80: Contas a Receber | S80: =C80='Plano de Contas'!C80 -> TRUE
A81: 1120199 | B81: S | C81: PROVISAO CREDITO LIQUID. DUVIDOSA | D81: C | E81: 1 | F81: Ativo | G81: Curto Prazo | H81: 11 | I81: 1.1.2.01.99 | J81: PROVISAO CREDITO LIQUID. DUVIDOSA | K81: Contas a receber | S81: =C81='Plano de Contas'!C81 -> TRUE
A82: 11201990001 | B82: A | C82: PROVISAO CREDITO LIQUID. DUVIDOSA | D82: C | E82: 1 | F82: Ativo | G82: Curto Prazo | H82: 16 | I82: - | J82: PROVISAO CREDITO LIQUID. DUVIDOSA | K82: Contas a receber | L82: Provisão p/ crédito liquidação duvidosa | S82: =C82='Plano de Contas'!C82 -> TRUE
A83: 113 | B83: S | C83: CREDITOS A RECEBER | D83: D | E83: 1 | F83: Ativo | G83: Curto Prazo | H83: 5 | I83: - | J83: CREDITOS A RECEBER | K83: Outros ativos | S83: =C83='Plano de Contas'!C83 -> TRUE
A84: 11301 | B84: S | C84: CREDITOS A RECEBER | D84: D | E84: 1 | F84: Ativo | G84: Curto Prazo | H84: 8 | I84: - | J84: CREDITOS A RECEBER | K84: Outros ativos | S84: =C84='Plano de Contas'!C84 -> TRUE
A85: 1130100 | B85: S | C85: FEDERACOES / SINDICATOS | D85: D | E85: 1 | F85: Ativo | G85: Curto Prazo | H85: 11 | I85: 1.1.3.01.00 | J85: FEDERACOES / SINDICATOS | K85: Outros ativos | S85: =C85='Plano de Contas'!C85 -> TRUE
A86: 11301000001 | B86: A | C86: CREDITOS A RECEBER | D86: D | E86: 1 | F86: Ativo | G86: Curto Prazo | H86: 16 | I86: - | J86: FEDERACOES / SINDICATOS | K86: Outros ativos | S86: =C86='Plano de Contas'!C86 -> TRUE
A87: 11301000002 | B87: A | C87: FENSEG | D87: D | E87: 1 | F87: Ativo | G87: Curto Prazo | H87: 16 | I87: - | J87: FEDERACOES / SINDICATOS | K87: Outros ativos | S87: =C87='Plano de Contas'!C87 -> TRUE
A88: 11301000003 | B88: A | C88: FENASAUDE | D88: D | E88: 1 | F88: Ativo | G88: Curto Prazo | H88: 16 | I88: - | J88: FEDERACOES / SINDICATOS | K88: Outros ativos | S88: =C88='Plano de Contas'!C88 -> TRUE
A89: 11301000004 | B89: A | C89: FENAPREVI | D89: D | E89: 1 | F89: Ativo | G89: Curto Prazo | H89: 16 | I89: - | J89: FEDERACOES / SINDICATOS | K89: Outros ativos | S89: =C89='Plano de Contas'!C89 -> TRUE
A90: 11301000005 | B90: A | C90: FENACAP | D90: D | E90: 1 | F90: Ativo | G90: Curto Prazo | H90: 16 | I90: - | J90: FEDERACOES / SINDICATOS | K90: Outros ativos | S90: =C90='Plano de Contas'!C90 -> TRUE
A91: 11301000006 | B91: A | C91: SINDICATO DAS SEGURADORAS | D91: D | E91: 1 | F91: Ativo | G91: Curto Prazo | H91: 16 | I91: - | J91: FEDERACOES / SINDICATOS | K91: Outros ativos | S91: =C91='Plano de Contas'!C91 -> TRUE
A92: 11301000007 | B92: A | C92: CNSIMO | D92: D | E92: 1 | F92: Ativo | G92: Curto Prazo | H92: 16 | I92: - | J92: FEDERACOES / SINDICATOS | K92: Outros ativos | S92: =C92='Plano de Contas'!C92 -> TRUE
A93: 11301000008 | B93: A | C93: CNSEG | D93: D | E93: 1 | F93: Ativo | G93: Curto Prazo | H93: 16 | I93: - | J93: FEDERACOES / SINDICATOS | K93: Outros ativos | S93: =C93='Plano de Contas'!C93 -> TRUE
A94: 1130101 | B94: S | C94: CREDITOS A RECEBER - OUTROS | D94: D | E94: 1 | F94: Ativo | G94: Curto Prazo | H94: 11 | I94: 1.1.3.01.01 | J94: CREDITOS A RECEBER - OUTROS | K94: Outros ativos | S94: =C94='Plano de Contas'!C94 -> TRUE
... A133: 11301080003 | B133: A | C133: ANTECIPACAO PIS S/ 13 SALARIO | D133: D | E133: 1 | F133: Ativo | G133: Curto Prazo | H133: 16 | I133: - | J133: ANTECIPACAO DE ENCARGOS S/ 13 SALARIO | K133: Outros ativos | S133: =C133='Plano de Contas'!C133 -> TRUE
A134: 1130109 | B134: S | C134: ANTECIPACAO DE IMPOSTOS S/ INSCRICAO DE EVENTOS | D134: D | E134: =LEFT(A134,1) -> 1 | F134: Ativo | G134: Curto Prazo | H134: =LEN(A134) -> 7 | I134: 1.1.3.01.09 | J134: =IF(H134<11,C134,IF(I134<>"-",C134,J133)) -> ANTECIPACAO DE IMPOSTOS S/ INSCRICAO DE EVENTOS | K134: Outros ativos | S134: =C134='Plano de Contas'!C134 -> TRUE
A135: 11301090001 | B135: A | C135: ANTECIPACAO ISS S/ INSCRICAO DE EVENTOS | D135: D | E135: =LEFT(A135,1) -> 1 | F135: Ativo | G135: Curto Prazo | H135: =LEN(A135) -> 11 | I135: - | J135: =IF(H135<11,C135,IF(I135<>"-",C135,J134)) -> ANTECIPACAO DE IMPOSTOS S/ INSCRICAO DE EVENTOS | K135: Outros ativos | S135: =C135='Plano de Contas'!C135 -> TRUE
A136: 11301090002 | B136: A | C136: ANTECIPACAO COFINS S/ INSCRICAO DE EVENTOS | D136: D | E136: =LEFT(A136,1) -> 1 | F136: Ativo | G136: Curto Prazo | H136: =LEN(A136) -> 11 | I136: - | J136: =IF(H136<11,C136,IF(I136<>"-",C136,J135)) -> ANTECIPACAO DE IMPOSTOS S/ INSCRICAO DE EVENTOS | K136: Outros ativos | S136: =C136='Plano de Contas'!C136 -> TRUE
A137: 11301090003 | B137: A | C137: ANTECIPACAO ISS S/ PATROCÍNIO DE EVENTOS | D137: D | E137: =LEFT(A137,1) -> 1 | F137: Ativo | G137: Curto Prazo | H137: =LEN(A137) -> 11 | I137: - | J137: =IF(H137<11,C137,IF(I137<>"-",C137,J136)) -> ANTECIPACAO DE IMPOSTOS S/ INSCRICAO DE EVENTOS | K137: Outros ativos | S137: =C137='Plano de Contas'!C137 -> TRUE
A138: 11301090004 | B138: A | C138: ANTECIPACAO COFINS S/ PATROCÍNIO DE EVENTOANTECIPACAO COFINS S/ PATROCÍNIO DE EVENTOS | D138: D | E138: =LEFT(A138,1) -> 1 | F138: Ativo | G138: Curto Prazo | H138: =LEN(A138) -> 11 | I138: - | J138: =IF(H138<11,C138,IF(I138<>"-",C138,J137)) -> ANTECIPACAO DE IMPOSTOS S/ INSCRICAO DE EVENTOS | K138: Outros ativos | S138: =C138='Plano de Contas'!C138 -> TRUE
A139: 114 | B139: S | C139: PARTES RELACIONADAS | D139: D | E139: 1 | F139: Ativo | G139: Curto Prazo | H139: 5 | I139: - | J139: PARTES RELACIONADAS | K139: Transações com partes relacionadas (Ativo) | L139: Transações com partes relacionadas (Ativo) | S139: =C139='Plano de Contas'!C139 -> TRUE
A140: 11401 | B140: S | C140: PARTES RELACIONADAS | D140: D | E140: 1 | F140: Ativo | G140: Curto Prazo | H140: 8 | I140: - | J140: PARTES RELACIONADAS | K140: Transações com partes relacionadas (Ativo) | L140: Transações com partes relacionadas (Ativo) | S140: =C140='Plano de Contas'!C140 -> TRUE
A141: 1140101 | B141: S | C141: PARTES RELACIONADAS | D141: D | E141: 1 | F141: Ativo | G141: Curto Prazo | H141: 11 | I141: 1.1.4.01.01 | J141: PARTES RELACIONADAS | K141: Transações com partes relacionadas (Ativo) | L141: Transações com partes relacionadas (Ativo) | S141: =C141='Plano de Contas'!C141 -> TRUE
A142: 11401010001 | B142: A | C142: PARTES RELACIONADAS | D142: D | E142: 1 | F142: Ativo | G142: Curto Prazo | H142: 16 | I142: - | J142: PARTES RELACIONADAS | K142: Transações com partes relacionadas (Ativo) | L142: Transações com partes relacionadas (Ativo) | S142: =C142='Plano de Contas'!C142 -> TRUE
A143: 115 | B143: S | C143: ALMOXARIFADO | D143: D | E143: 1 | F143: Ativo | G143: Curto Prazo | H143: 5 | I143: - | J143: ALMOXARIFADO | K143: Outros ativos | S143: =C143='Plano de Contas'!C143 -> TRUE
A144: 11501 | B144: S | C144: ALMOXARIFADO | D144: D | E144: 1 | F144: Ativo | G144: Curto Prazo | H144: 8 | I144: - | J144: ALMOXARIFADO | K144: Outros ativos | S144: =C144='Plano de Contas'!C144 -> TRUE
A145: 1150101 | B145: S | C145: MATERIAIS DIVERSOS | D145: D | E145: 1 | F145: Ativo | G145: Curto Prazo | H145: 11 | I145: 1.1.5.01.01 | J145: MATERIAIS DIVERSOS | K145: Outros ativos | S145: =C145='Plano de Contas'!C145 -> TRUE
A146: 11501010001 | B146: A | C146: MATERIAL DE ESCRITORIO | D146: D | E146: 1 | F146: Ativo | G146: Curto Prazo | H146: 16 | I146: - | J146: MATERIAIS DIVERSOS | K146: Outros ativos | S146: =C146='Plano de Contas'!C146 -> TRUE
A147: 11501010002 | B147: A | C147: MATERIAL SERVICOS/COPA | D147: D | E147: 1 | F147: Ativo | G147: Curto Prazo | H147: 16 | I147: - | J147: MATERIAIS DIVERSOS | K147: Outros ativos | S147: =C147='Plano de Contas'!C147 -> TRUE
A148: 11501010003 | B148: A | C148: MATERIAL DE LIMPEZA | D148: D | E148: 1 | F148: Ativo | G148: Curto Prazo | H148: 16 | I148: - | J148: MATERIAIS DIVERSOS | K148: Outros ativos | S148: =C148='Plano de Contas'!C148 -> TRUE
A149: 11501010004 | B149: A | C149: MATERIAL DE INFORMATICA | D149: D | E149: 1 | F149: Ativo | G149: Curto Prazo | H149: 16 | I149: - | J149: MATERIAIS DIVERSOS | K149: Outros ativos | S149: =C149='Plano de Contas'!C149 -> TRUE
A150: 11501010005 | B150: A | C150: MATERIAL DE MANUTENCAO | D150: D | E150: 1 | F150: Ativo | G150: Curto Prazo | H150: 16 | I150: - | J150: MATERIAIS DIVERSOS | K150: Outros ativos | S150: =C150='Plano de Contas'!C150 -> TRUE
A151: 11501010006 | B151: A | C151: MATERIAL DE EVENTOS | D151: D | E151: 1 | F151: Ativo | G151: Curto Prazo | H151: 16 | I151: - | J151: MATERIAIS DIVERSOS | K151: Outros ativos | S151: =C151='Plano de Contas'!C151 -> TRUE
A152: 116 | B152: S | C152: DESPESAS ANTECIPADAS | D152: D | E152: 1 | F152: Ativo | G152: Curto Prazo | H152: 5 | I152: - | J152: DESPESAS ANTECIPADAS | K152: Outros ativos | S152: =C152='Plano de Contas'!C152 -> TRUE
A153: 11601 | B153: S | C153: DESPESAS ANTECIPADAS | D153: D | E153: 1 | F153: Ativo | G153: Curto Prazo | H153: 8 | I153: - | J153: DESPESAS ANTECIPADAS | K153: Outros ativos | S153: =C153='Plano de Contas'!C153 -> TRUE
A154: 1160101 | B154: S | C154: DESPESAS ADMINISTRATIVAS ANTECIPADAS | D154: D | E154: 1 | F154: Ativo | G154: Curto Prazo | H154: 11 | I154: 1.1.6.01.01 | J154: DESPESAS ADMINISTRATIVAS ANTECIPADAS | K154: Outros ativos | S154: =C154='Plano de Contas'!C154 -> TRUE
... A165: 12101 | B165: S | C165: CREDITOS E VALORES | D165: D | E165: 1 | F165: Ativo | G165: Longo Prazo | H165: 8 | I165: - | J165: CREDITOS E VALORES | K165: Outros ativos | S165: =C165='Plano de Contas'!C165 -> TRUE
A166: 1210101 | B166: S | C166: DIREITOS CREDITORIOS | D166: D | E166: 1 | F166: Ativo | G166: Longo Prazo | H166: 11 | I166: 1.2.1.01.01 | J166: DIREITOS CREDITORIOS | K166: Depósitos judiciais | L166: Depósitos judiciais | S166: =C166='Plano de Contas'!C166 -> TRUE
A167: 12101010001 | B167: A | C167: CONVENIO DPVAT | D167: D | E167: 1 | F167: Ativo | G167: Longo Prazo | H167: 16 | I167: - | J167: DIREITOS CREDITORIOS | K167: Depósitos judiciais | L167: Depósitos judiciais | S167: =C167='Plano de Contas'!C167 -> TRUE
A168: 12101010002 | B168: A | C168: DEPOSITOS JUDICIAIS-DPVAT | D168: D | E168: 1 | F168: Ativo | G168: Longo Prazo | H168: 16 | I168: - | J168: DIREITOS CREDITORIOS | K168: Depósitos judiciais | L168: Depósitos judiciais | S168: =C168='Plano de Contas'!C168 -> TRUE
A169: 1210102 | B169: A | C169: DEPOSITOS JUDICIAIS | D169: D | E169: 1 | F169: Ativo | G169: Longo Prazo | H169: 11 | I169: 1.2.1.01.02 | J169: DEPOSITOS JUDICIAIS | K169: Depósitos judiciais | L169: Depósitos judiciais | S169: =C169='Plano de Contas'!C169 -> TRUE
A170: 12101020001 | B170: A | C170: DEPOSITOS JUDICIAIS - TRABALHISTAS | D170: D | E170: 1 | F170: Ativo | G170: Longo Prazo | H170: 16 | I170: - | J170: DEPOSITOS JUDICIAIS | K170: Depósitos judiciais | L170: Depósitos judiciais | S170: =C170='Plano de Contas'!C170 -> TRUE
A171: 12102 | B171: S | C171: PARTES RELACIONADAS | D171: D | E171: 1 | F171: Ativo | G171: Longo Prazo | H171: 8 | I171: - | J171: PARTES RELACIONADAS | K171: Transações com partes relacionadas (Ativo) | L171: Transações com partes relacionadas (Ativo) | S171: =C171='Plano de Contas'!C171 -> TRUE
A172: 1210201 | B172: S | C172: PARTES RELACIONADAS | D172: D | E172: 1 | F172: Ativo | G172: Longo Prazo | H172: 11 | I172: 1.2.1.02.01 | J172: PARTES RELACIONADAS | K172: Transações com partes relacionadas (Ativo) | L172: Transações com partes relacionadas (Ativo) | S172: =C172='Plano de Contas'!C172 -> TRUE
A173: 12102010001 | B173: A | C173: PARTES RELACIONADAS | D173: D | E173: 1 | F173: Ativo | G173: Longo Prazo | H173: 16 | I173: - | J173: PARTES RELACIONADAS | K173: Transações com partes relacionadas (Ativo) | L173: Transações com partes relacionadas (Ativo) | S173: =C173='Plano de Contas'!C173 -> TRUE
A174: 12103 | B174: S | C174: EMPRESTIMOS A FUNCIONÁRIOS | D174: D | E174: 1 | F174: Ativo | G174: Longo Prazo | H174: 8 | I174: - | J174: EMPRESTIMOS A FUNCIONÁRIOS | K174: Outros ativos | S174: =C174='Plano de Contas'!C174 -> TRUE
A175: 1210301 | B175: S | C175: EMPRESTIMOS A FUNCIONÁRIOS | D175: D | E175: 1 | F175: Ativo | G175: Longo Prazo | H175: 11 | I175: 1.2.1.03.01 | J175: EMPRESTIMOS A FUNCIONÁRIOS | K175: Outros ativos | S175: =C175='Plano de Contas'!C175 -> TRUE
A176: 12103010001 | B176: A | C176: EMPRESTIMOS A FUNCIONÁRIOS | D176: D | E176: 1 | F176: Ativo | G176: Longo Prazo | H176: 16 | I176: - | J176: EMPRESTIMOS A FUNCIONÁRIOS | K176: Outros ativos | S176: =C176='Plano de Contas'!C176 -> TRUE
A177: 122 | B177: S | C177: INVESTIMENTOS | D177: D | E177: 1 | F177: Ativo | G177: Longo Prazo | H177: 5 | I177: - | J177: INVESTIMENTOS | K177: Investimentos | S177: =C177='Plano de Contas'!C177 -> TRUE
A178: 12201 | B178: S | C178: PARTICIPACOES EM SOCIEDADES | D178: D | E178: 1 | F178: Ativo | G178: Longo Prazo | H178: 8 | I178: - | J178: PARTICIPACOES EM SOCIEDADES | K178: Investimentos | L178: Participações em sociedades | S178: =C178='Plano de Contas'!C178 -> TRUE
A179: 1220101 | B179: S | C179: PARTICIPACOES EM SOCIEDADES | D179: D | E179: 1 | F179: Ativo | G179: Longo Prazo | H179: 11 | I179: 1.2.2.01.01 | J179: PARTICIPACOES EM SOCIEDADES | K179: Investimentos | L179: Participações em sociedades | S179: =C179='Plano de Contas'!C179 -> TRUE
...

Sheet Centro de lucro
A1: Centro de Custo | B1: Descrição MXM | C1: Gerência | D1: Superintendência | E1: Diretoria | F1: Classificação BP e DRE | G1: ESTRUTURA | H1: CÓDIGO GERÊNCIA | I1: CÓDIGO SUPERINTÊNDENCIA | J1: CÓDIGO DIRETORIA
A2: F220000001 | B2: ASSESSORIA | C2: ASSESSORIA | D2: ASSESSORIA | E2: ASSESSORIA | F2: 0 | H2: ASLG | I2: ASLG | J2: ASLG
A3: F100000000 | B3: CONSELHO DIRETOR | C3: CONSELHO DIRETOR | D3: CONSELHO DIRETOR | E3: CONSELHO DIRETOR | F3: 0 | H3: CONSELHO DIRETOR | I3: CONSELHO DIRETOR | J3: CONSELHO DIRETOR
A4: F200000000 | B4: PRESIDÊNCIA | C4: PRESIDENCIA | D4: PRESIDENCIA | E4: PRESIDENCIA | F4: SISEG | G4: FPR0001 | H4: PRESI | I4: PRESI | J4: PRESI
A5: F200000001 | B5: SECRETARIA GERAL E GOV. CORPORATIVA | C5: SECRETARIA GERAL E GOVERNANÇA CORPORATIVA | D5: SECRETARIA GERAL E GOVERNANÇA CORPORATIVA | E5: SUPERINTENDÊNCIA EXECUTIVA DE COORDENAÇÃO DO GABINETE | F5: 0 | G5: FSU0113 | H5: SEGER | I5: SEGER | J5: SUGAB
A6: F200000002 | B6: CONTROLES INTERNOS E COMPLIANCE | C6: CONTROLES INTERNOS E COMPLIANCE | D6: PRESIDENCIA | E6: PRESIDENCIA | F6: 0 | H6: CICOM | I6: PRESI | J6: PRESI
A7: F200100000 | B7: SUP. EXEC. DE COORDENAÇÃO DE GABINETE | C7: SUPERINTENDÊNCIA EXECUTIVA DE COORDENAÇÃO DO GABINETE | D7: SUPERINTENDÊNCIA EXECUTIVA DE COORDENAÇÃO DO GABINETE | E7: SUPERINTENDÊNCIA EXECUTIVA DE COORDENAÇÃO DO GABINETE | F7: 0 | G7: FSE0105 | H7: SUGAB | I7: SUGAB | J7: SUGAB
A8: F203000000 | B8: SUP. EXEC. DE COMUNICAÇÃO E MARKETING | C8: SUPERINTENDÊNCIA EXECUTIVA DE COMUNICAÇÃO E MARKETING | D8: SUPERINTENDÊNCIA EXECUTIVA DE COMUNICAÇÃO E MARKETING | E8: SUPERINTENDÊNCIA EXECUTIVA DE COMUNICAÇÃO E MARKETING | F8: 0 | G8: FSE0104 | H8: SUCOM | I8: SUCOM | J8: SUCOM
A9: F203000003 | B9: CEDOM | C9: CENTRO DE DOCUMENTAÇÃO E MEMÓRIA | D9: SUPERINTENDÊNCIA EXECUTIVA DE COMUNICAÇÃO E MARKETING | E9: SUPERINTENDÊNCIA EXECUTIVA DE COMUNICAÇÃO E MARKETING | F9: 0 | H9: GEDOM | I9: SUCOM | J9: SUCOM
A10: F203000004 | B10: REVISTA DE SEGUROS | C10: REVISTA DE SEGUROS | D10: SUPERINTENDÊNCIA EXECUTIVA DE COMUNICAÇÃO E MARKETING | E10: SUPERINTENDÊNCIA EXECUTIVA DE COMUNICAÇÃO E MARKETING | F10: 0 | H10: REVSEG | I10: SUCOM | J10: SUCOM
A11: F203000005 | B11: GERÊNCIA DE COMUNICAÇÃO | C11: GERÊNCIA DE COMUNICAÇÃO | D11: SUPERINTENDÊNCIA EXECUTIVA DE COMUNICAÇÃO E MARKETING | E11: SUPERINTENDÊNCIA EXECUTIVA DE COMUNICAÇÃO E MARKETING | F11: 0 | G11: FGE0129 | H11: GECOMUN | I11: SUCOM | J11: SUCOM
A12: F203000006 | B12: GERÊNCIA DE R. C /IMPRENSA E PUBLICAÇÕES | C12: GERÊNCIA DE RELAÇÕES COM IMPRENSA E PUBLICAÇÕES | D12: SUPERINTENDÊNCIA EXECUTIVA DE COMUNICAÇÃO E MARKETING | E12: SUPERINTENDÊNCIA EXECUTIVA DE COMUNICAÇÃO E MARKETING | F12: 0 | G12: GERIN | H12: GERIN | I12: SUCOM | J12: SUCOM
A13: F203000007 | B13: GERÊNCIA DE MARKETING | C13: GERÊNCIA DE MARKETING | D13: SUPERINTENDÊNCIA EXECUTIVA DE COMUNICAÇÃO E MARKETING | E13: SUPERINTENDÊNCIA EXECUTIVA DE COMUNICAÇÃO E MARKETING | F13: 0 | G13: FGE0131 | H13: GEMKT | I13: SUCOM | J13: SUCOM
A14: F250000000 | B14: DIRETORIA DE RELAÇÕES INSTITUCIONAIS | C14: DIRETORIA DE RELAÇÕES INSTITUCIONAIS | D14: DIRETORIA DE RELAÇÕES INSTITUCIONAIS | E14: DIRETORIA DE RELAÇÕES INSTITUCIONAIS | F14: 0 | G14: FDIRIN | H14: DIRIN | I14: DIRIN | J14: DIRIN
A15: F251100000 | B15: SUPERINTENDÊNCIA DE REL. INSTITUCIONAIS | C15: SUPERINTENDÊNCIA DE RELAÇÕES INSTITUCIONAIS | D15: SUPERINTENDÊNCIA DE RELAÇÕES INSTITUCIONAIS | E15: DIRETORIA DE RELAÇÕES INSTITUCIONAIS | F15: 0 | G15: FSU0201 | H15: SURIN | I15: SURIN | J15: DIRIN
A16: F251101000 | B16: GERÊNCIA ADMINISTRATIVA - DF | C16: SUPERINTENDÊNCIA DE RELAÇÕES INSTITUCIONAIS | D16: SUPERINTENDÊNCIA DE RELAÇÕES INSTITUCIONAIS | E16: DIRETORIA DE RELAÇÕES INSTITUCIONAIS | F16: 0 | H16: SURIN | I16: SURIN | J16: DIRIN
A17: F251102000 | B17: GERÊNCIA DE REL C/ ESTADOS E MUNICÍPIOS | C17: GERÊNCIA DE RELAÇÕES COM ESTADOS E MUNICÍPIOS | D17: SUPERINTENDÊNCIA DE RELAÇÕES INSTITUCIONAIS | E17: DIRETORIA DE RELAÇÕES INSTITUCIONAIS | F17: 0 | G17: FGE0201 | H17: GEREM | I17: SURIN | J17: DIRIN
A18: F251103000 | B18: GERÊNCIA DE RELAÇÕES COM SENADO | C18: GERÊNCIA DE RELAÇÕES COM SENADO | D18: SUPERINTENDÊNCIA DE RELAÇÕES INSTITUCIONAIS | E18: DIRETORIA DE RELAÇÕES INSTITUCIONAIS | F18: 0 | G18: FGE0202 | H18: GERSEN | I18: SURIN | J18: DIRIN
A19: F251104000 | B19: GERÊNCIA DE RELAÇÕES COM A CÂMARA | C19: GERÊNCIA DE RELAÇÕES COM A CÂMARA | D19: SUPERINTENDÊNCIA DE RELAÇÕES INSTITUCIONAIS | E19: DIRETORIA DE RELAÇÕES INSTITUCIONAIS | F19: 0 | G19: FGE0203 | H19: GERCAM | I19: SURIN | J19: DIRIN
A20: F251105000 | B20: COORDENAÇÃO ADMINISTRATIVA DF | C20: SUPERINTENDÊNCIA DE RELAÇÕES INSTITUCIONAIS | D20: SUPERINTENDÊNCIA DE RELAÇÕES INSTITUCIONAIS | E20: DIRETORIA DE RELAÇÕES INSTITUCIONAIS | F20: 0 | H20: SURIN | I20: SURIN | J20: DIRIN
A21: F310000000 | B21: DIRETORIA JURÍDICA | C21: DIRETORIA JURÍDICA | D21: DIRETORIA JURÍDICA | E21: DIRETORIA JURÍDICA | F21: 0 | G21: FGT0101 | H21: DIJUR | I21: DIJUR | J21: DIJUR
A22: F311100000 | B22: SUPERINTENDÊNCIA JURÍDICA | C22: SUPERINTENDÊNCIA JURÍDICA | D22: SUPERINTENDÊNCIA JURÍDICA | E22: DIRETORIA JURÍDICA | F22: 0 | G22: FSU0101 | H22: SEJUR | I22: SEJUR | J22: DIJUR
A23: F311100001 | B23: ASSESSORIA JURÍDICA | C23: ASSESSORIA JURÍDICA | D23: SUPERINTENDÊNCIA JURÍDICA | E23: DIRETORIA JURÍDICA | F23: 0 | H23: ASSESSORIA JURÍDICA | I23: SEJUR | J23: DIJUR
A24: F311101000 | B24: GERÊNCIA DE CONTENCIOSO | C24: GERÊNCIA DE CONTENCIOSO | D24: SUPERINTENDÊNCIA JURÍDICA | E24: DIRETORIA JURÍDICA | F24: 0 | G24: FGE0101 | H24: GECOS | I24: SEJUR | J24: DIJUR
A25: F311102000 | B25: GERÊNCIA DE CONSULTORIAS | C25: GERÊNCIA DE CONSULTORIAS | D25: SUPERINTENDÊNCIA JURÍDICA | E25: DIRETORIA JURÍDICA | F25: Outras | G25: FGE0102 | H25: GECON | I25: SEJUR | J25: DIJUR
A26: F311103000 | B26: GERÊNCIA JURÍDICA CORP., DE NEGÓCIOS | C26: GERÊNCIA JURÍDICA CORP., DE NEGÓCIOS | D26: SUPERINTENDÊNCIA JURÍDICA | E26: DIRETORIA JURÍDICA | F26: Outras | G26: FGE0136 | H26: GJNECO | I26: SEJUR | J26: DIJUR
A27: F320000000 | B27: DIRETORIA DE SUSTENTABILIDADE E CONSUMO | C27: DIRETORIA DE SUSTENTABILIDADE E CONSUMO | D27: DIRETORIA DE SUSTENTABILIDADE E CONSUMO | E27: DIRETORIA DE SUSTENTABILIDADE E CONSUMO | F27: 0 | G27: FGT0102 | H27: DISEC | I27: DISEC | J27: DISEC
A28: F321100000 | B28: SUPERINTENDÊNCIA DE EVENTOS | C28: SUPERINTENDÊNCIA DE EVENTOS | D28: SUPERINTENDÊNCIA DE EVENTOS | E28: SUPERINTENDÊNCIA EXECUTIVA DE COORDENAÇÃO DO GABINETE | F28: Outras | G28: FSU0106 | H28: SUPEV | I28: SUPEV | J28: SUGAB
A29: F321101000 | B29: GERÊNCIA DE EVENTOS | C29: GERÊNCIA DE EVENTOS | D29: SUPERINTENDÊNCIA DE EVENTOS | E29: SUPERINTENDÊNCIA EXECUTIVA DE COORDENAÇÃO DO GABINETE | F29: 0 | G29: FGE0124 | H29: GEEVE | I29: SUPEV | J29: SUGAB
A30: F321102000 | B30: GERÊNCIA DE PROJETOS INSTITUCIONAIS | C30: GERÊNCIA DE PROJETOS INSTITUCIONAIS | D30: SUPERINTENDÊNCIA DE EVENTOS | E30: SUPERINTENDÊNCIA EXECUTIVA DE COORDENAÇÃO DO GABINETE | F30: 0 | G30: FGE204 | H30: GEPIT | I30: SUPEV | J30: SUGAB
A31: F330000000 | B31: DIRET. DE A. CORP. E REL. SINDICAIS | C31: DIRETORIA DE ASSUNTOS CORPORATIVOS E RELAÇÕES SINDICAIS | D31: DIRETORIA DE ASSUNTOS CORPORATIVOS E RELAÇÕES SINDICAIS | E31: DIRETORIA DE ASSUNTOS CORPORATIVOS E RELAÇÕES SINDICAIS | F31: 0 | G31: FDAFC | H31: DICOR | I31: DICOR | J31: DICOR
A32: F331000000 | B32: DIRETORIA DE SERVIÇOS AS ASSOCIADAS | C32: DIRETORIA DE SERVIÇOS AS ASSOCIADAS | D32: DIRETORIA DE SERVIÇOS AS ASSOCIADAS | E32: DIRETORIA DE SERVIÇOS AS ASSOCIADAS | G32: FDS0103 | H32: DISERV | I32: DISERV | J32: DISERV
A33: F331001000 | B33: GERÊNCIA DE SEGURANÇA DA INFORMAÇÃO | C33: GERÊNCIA DE SEGURANÇA DA INFORMAÇÃO | D33: DIRETORIA DE SERVIÇOS AS ASSOCIADAS | E33: DIRETORIA DE SERVIÇOS AS ASSOCIADAS | H33: GESEG | I33: DISERV | J33: DISERV
A34: F331101000 | B34: GERÊNCIA DE PREVENÇÃO E COMBATE A FRAUDE | C34: GERÊNCIA DE PREVENÇÃO E COMBATE A FRAUDE | D34: SUPERINTENDÊNCIA DE PRODUTOS E OPERAÇÕES | E34: DIRETORIA DE SERVIÇOS AS ASSOCIADAS | F34: Sistema Nacional de Gravames - SNG | G34: FGE0114 | H34: GEPCF | I34: SUPRO | J34: DISERV
A35: F331101001 | B35: FORNEC. DE INF. P/ PROTEÇÃO AO SEGURO | C35: GERÊNCIA DE PREVENÇÃO E COMBATE A FRAUDE | D35: SUPERINTENDÊNCIA DE PRODUTOS E OPERAÇÕES | E35: DIRETORIA DE SERVIÇOS AS ASSOCIADAS | F35: SISEG | G35: FGE0114 | H35: FORINF | I35: SUPRO | J35: DISERV
A36: F331101002 | B36: ASSINATURAS E REGRAS | C36: GERÊNCIA DE PREVENÇÃO E COMBATE A FRAUDE | D36: SUPERINTENDÊNCIA DE PRODUTOS E OPERAÇÕES | E36: DIRETORIA DE SERVIÇOS AS ASSOCIADAS | F36: SISEG | G36: FGE0114 | H36: ASSINT | I36: SUPRO | J36: DISERV
A37: F331101003 | B37: PROCEDIMENTOS CRIMINAIS | C37: GERÊNCIA DE PREVENÇÃO E COMBATE A FRAUDE | D37: SUPERINTENDÊNCIA DE PRODUTOS E OPERAÇÕES | E37: DIRETORIA DE SERVIÇOS AS ASSOCIADAS | F37: SISEG | G37: FGE0114 | H37: PROCED | I37: SUPRO | J37: DISERV
A38: F331101004 | B38: PROCEDIMENTOS CRIMINAIS - AUTO | C38: GERÊNCIA DE PREVENÇÃO E COMBATE A FRAUDE | D38: SUPERINTENDÊNCIA DE PRODUTOS E OPERAÇÕES | E38: DIRETORIA DE SERVIÇOS AS ASSOCIADAS | F38: SISEG | G38: FGE0114 | H38: PROCED | I38: SUPRO | J38: DISERV
A39: F331101005 | B39: PROCEDIMENTOS CRIMINAIS - PATRIMONIAL | C39: GERÊNCIA DE PREVENÇÃO E COMBATE A FRAUDE | D39: SUPERINTENDÊNCIA DE PRODUTOS E OPERAÇÕES | E39: DIRETORIA DE SERVIÇOS AS ASSOCIADAS | F39: SISEG | G39: FGE0114 | H39: PROCED | I39: SUPRO | J39: DISERV
A40: F331101006 | B40: PROCEDIMENTOS CRIMINAIS - TRANSPORTES | C40: GERÊNCIA DE PREVENÇÃO E COMBATE A FRAUDE | D40: SUPERINTENDÊNCIA DE PRODUTOS E OPERAÇÕES | E40: DIRETORIA DE SERVIÇOS AS ASSOCIADAS | F40: SISEG | G40: FGE0114 | H40: PROCED | I40: SUPRO | J40: DISERV
A41: F331101007 | B41: ASSINATURAS - AUTO | C41: GERÊNCIA DE PREVENÇÃO E COMBATE A FRAUDE | D41: SUPERINTENDÊNCIA DE PRODUTOS E OPERAÇÕES | E41: DIRETORIA DE SERVIÇOS AS ASSOCIADAS | F41: SISEG | G41: FGE0114 | H41: PROCED | I41: SUPRO | J41: DISERV
A42: F331101008 | B42: ASSINATURAS - PATRIMONIAL | C42: GERÊNCIA DE PREVENÇÃO E COMBATE A FRAUDE | D42: SUPERINTENDÊNCIA DE PRODUTOS E OPERAÇÕES | E42: DIRETORIA DE SERVIÇOS AS ASSOCIADAS | F42: SISEG | G42: FGE0114 | H42: PROCED | I42: SUPRO | J42: DISERV
A43: F331101009 | B43: ASSINATURAS - TRANSPORTES | C43: GERÊNCIA DE PREVENÇÃO E COMBATE A FRAUDE | D43: SUPERINTENDÊNCIA DE PRODUTOS E OPERAÇÕES | E43: DIRETORIA DE SERVIÇOS AS ASSOCIADAS | F43: SISEG | G43: FGE0114 | H43: PROCED | I43: SUPRO | J43: DISERV
A44: F331101010 | B44: ASSINATURAS - RURAL | C44: GERÊNCIA DE PREVENÇÃO E COMBATE A FRAUDE | D44: SUPERINTENDÊNCIA DE PRODUTOS E OPERAÇÕES | E44: DIRETORIA DE SERVIÇOS AS ASSOCIADAS | F44: SISEG | G44: FGE0114 | H44: PROCED | I44: SUPRO | J44: DISERV
A45: F331101011 | B45: ASSINATURAS - DANOS CORPORAIS | C45: GERÊNCIA DE PREVENÇÃO E COMBATE A FRAUDE | D45: SUPERINTENDÊNCIA DE PRODUTOS E OPERAÇÕES | E45: DIRETORIA DE SERVIÇOS AS ASSOCIADAS | F45: SISEG | G45: FGE0114 | H45: PROCED | I45: SUPRO | J45: DISERV
... A109: F331104003 | B109: SIRCOF REGISTROS | C109: GERÊNCIA DE SERVIÇO NACIONAL DE GRAVAMES | D109: DIRETORIA DE SERVIÇOS AS ASSOCIADAS | E109: DIRETORIA DE SERVIÇOS AS ASSOCIADAS | F109: Sistema de Contratos (Ex-Sircof) | G109: FGE0109 | H109: GEIRC | I109: DISERV | J109: DISERV
A110: F331105000 | B110: GERÊNCIA DE SISTEMAS | C110: GERÊNCIA DE SISTEMAS | D110: DIRETORIA DE SERVIÇOS AS ASSOCIADAS | E110: DIRETORIA DE SERVIÇOS AS ASSOCIADAS | G110: FGE0112 | H110: GERSI | I110: DISERV | J110: DISERV
A111: F331107000 | B111: GERÊNCIA DE ATENDIMENTO/PÓS VENDA | C111: GERÊNCIA DE ATENDIMENTO/PÓS-VENDA | D111: SUPERINTENDÊNCIA DE NEGÓCIOS | E111: DIRETORIA DE SERVIÇOS AS ASSOCIADAS | F111: Outras | G111: FGE0113 | H111: GEAPV | I111: DISERV | J111: DISERV
A112: F331108000 | B112: GERÊNCIA COMERCIAL | C112: GERÊNCIA COMERCIAL | D112: SUPERINTENDÊNCIA DE NEGÓCIOS | E112: DIRETORIA DE SERVIÇOS AS ASSOCIADAS | F112: SISEG | G112: FGE0128 | H112: GECOM | I112: DISERV | J112: DISERV
A113: F331109000 | B113: GERÊNCIA DE MARKETING COMERCIAL | C113: GERÊNCIA DE MARKETING COMERCIAL | D113: SUPERINTENDÊNCIA DE NEGÓCIOS | E113: DIRETORIA DE SERVIÇOS AS ASSOCIADAS | F113: SISEG | G113: FGE0134 | H113: GEMKCO | I113: DISERV | J113: DITEC
A114: F331110000 | B114: GERÊNCIA DE INFRAESTRUTURA | C114: GERÊNCIA DE INFRAESTRUTURA | D114: DIRETORIA DE SERVIÇOS AS ASSOCIADAS | E114: DIRETORIA DE SERVIÇOS AS ASSOCIADAS | G114: FGE0135 | H114: GEINFRA | I114: DISERV | J114: DISERV
A115: F331112000 | B115: SUPERINTENDÊNCIA DE PROJETOS ESPECIAIS | C115: SUPERINTENDÊNCIA DE PROJETOS ESPECIAIS | D115: SUPERINTENDÊNCIA DE PROJETOS ESPECIAIS | E115: DIRETORIA DE SERVIÇOS AS ASSOCIADAS | G115: FSU0116 | H115: SUPRE | I115: SUPRE | J115: DISERV
A116: F331113000 | B116: GERENCIA DE GOVERNANCA DE TI | C116: DIRETORIA DE SERVIÇOS AS ASSOCIADAS | D116: DIRETORIA DE SERVIÇOS AS ASSOCIADAS | E116: DIRETORIA DE SERVIÇOS AS ASSOCIADAS | F116: SISEG | G116: FGE0137 | H116: GEGVTI | I116: DISERV | J116: DISERV
A117: F332000000 | B117: DIRET. TÉC. DE E. E DE REL.REGULATÓRIAS | C117: DIRETORIA TÉCNICA, DE ESTUDOS E DE RELAÇÕES REGULATÓRIAS | D117: DIRETORIA TÉCNICA, DE ESTUDOS E DE RELAÇÕES REGULATÓRIAS | E117: DIRETORIA TÉCNICA, DE ESTUDOS E DE RELAÇÕES REGULATÓRIAS | F117: 0 | G117: FDTEC | H117: DITEC | I117: DITEC | J117: DITEC
A118: F332100000 | B118: SUP. DE R. DE CONSUMO E SUSTENTABILIDADE | C118: SUPERINTENDÊNCIA DE RELAÇŌES DE CONSUMO E SUSTENTABILIDADE | D118: SUPERINTENDÊNCIA DE RELAÇŌES DE CONSUMO E SUSTENTABILIDADE | E118: DIRETORIA DE SUSTENTABILIDADE E CONSUMO | F118: 0 | G118: FSU0107 | H118: SUREC | I118: SUREC | J118: DISEC
A119: F332101000 | B119: GERÊNCIA DE CONDUTA DE MERCADO E RI | C119: GERÊNCIA DE CONDUTA DE MERCADO E RI | D119: SUPERINTENDÊNCIA DE RELAÇŌES DE CONSUMO E SUSTENTABILIDADE | E119: DIRETORIA DE SUSTENTABILIDADE E DE RELAÇŌES DE CONSUMO | F119: 0
A120: F332200000 | B120: SUPERINTENDÊNCIA DE ESTUDOS E PROJETOS | C120: SUPERINTENDÊNCIA DE ESTUDOS E PROJETOS | D120: SUPERINTENDÊNCIA DE ESTUDOS E PROJETOS | E120: DIRETORIA TÉCNICA, DE ESTUDOS E DE RELAÇÕES REGULATÓRIAS | F120: 0 | G120: FSU0102 | H120: SUESP | I120: SUESP | J120: DITEC
A121: F332300000 | B121: SUPERINTENDÊNCIA DE ACOMP. TÉCNICO | C121: SUPERINTENDÊNCIA DE ACOMPANHAMENTO TÉCNICO | D121: SUPERINTENDÊNCIA DE ACOMPANHAMENTO TÉCNICO | E121: DIRETORIA TÉCNICA, DE ESTUDOS E DE RELAÇÕES REGULATÓRIAS | F121: 0 | G121: FSU0105 | H121: SUPAT | I121: SUPAT | J121: DITEC
A122: F333100000 | B122: SUPERINTENDÊNCIA DE ADM. E FINANÇAS | C122: SUPERINTENDÊNCIA DE ADMINISTRAÇÃO E FINANÇAS | D122: SUPERINTENDÊNCIA DE ADMINISTRAÇÃO E FINANÇAS | E122: DIRETORIA DE ASSUNTOS CORPORATIVOS E RELAÇÕES SINDICAIS | F122: 0 | G122: FSU0104 | H122: SUAFI | I122: SUAFI | J122: DICOR
A123: F333101000 | B123: GERÊNCIA ADMINISTRATIVA | C123: GERÊNCIA ADMINISTRATIVA | D123: SUPERINTENDÊNCIA DE ADMINISTRAÇÃO E FINANÇAS | E123: DIRETORIA DE ASSUNTOS CORPORATIVOS E RELAÇÕES SINDICAIS | F123: Aluguéis | G123: FGE0104 | H123: GEADM | I123: SUAFI | J123: DICOR
A124: F333103000 | B124: GERÊNCIA FINANCEIRA | C124: GERÊNCIA FINANCEIRA | D124: SUPERINTENDÊNCIA DE ADMINISTRAÇÃO E FINANÇAS | E124: DIRETORIA DE ASSUNTOS CORPORATIVOS E RELAÇÕES SINDICAIS | F124: Aluguéis | G124: FGE0106 | H124: GEFIN | I124: SUAFI | J124: DICOR
A125: F333104000 | B125: GERÊNCIA OPERACIONAL | C125: GERÊNCIA OPERACIONAL | D125: SUPERINTENDÊNCIA DE ADMINISTRAÇÃO E FINANÇAS | E125: DIRETORIA DE ASSUNTOS CORPORATIVOS E RELAÇÕES SINDICAIS | F125: 0 | G125: FSU0108 | H125: SUPOC | I125: SUPOC | J125: DICOR
A126: F333105000 | B126: GERÊNCIA DE TECNOLOGIA E SISTEMAS | C126: GERÊNCIA DE TECNOLOGIA E SISTEMAS | D126: SUPERINTENDÊNCIA DE ADMINISTRAÇÃO E FINANÇAS | E126: DIRETORIA DE ASSUNTOS CORPORATIVOS E RELAÇÕES SINDICAIS | F126: 0 | G126: FGE0132 | H126: GETCS | I126: SUAFI | J126: DICOR
A127: F333200000 | B127: SUP. DE ORÇAMENTO E CONTABILIDADE | C127: SUPERINTENDÊNCIA DE ORÇAMENTO E CONTABILIDADE | D127: SUPERINTENDÊNCIA DE ORÇAMENTO E CONTABILIDADE | E127: DIRETORIA DE ASSUNTOS CORPORATIVOS E RELAÇÕES SINDICAIS | F127: 0 | G127: FSU0108 | H127: SUPOC | I127: SUPOC | J127: DICOR
A128: F333201000 | B128: GERÊNCIA DE ORÇAMENTO | C128: GERÊNCIA DE ORÇAMENTO | D128: SUPERINTENDÊNCIA DE ORÇAMENTO E CONTABILIDADE | E128: DIRETORIA DE ASSUNTOS CORPORATIVOS E RELAÇÕES SINDICAIS | F128: 0 | G128: FGE0108 | H128: GEORC | I128: SUPOC | J128: DICOR
A129: F333202000 | B129: GERÊNCIA DE CONTABILIDADE | C129: GERÊNCIA DE CONTABILIDADE | D129: SUPERINTENDÊNCIA DE ORÇAMENTO E CONTABILIDADE | E129: DIRETORIA DE ASSUNTOS CORPORATIVOS E RELAÇÕES SINDICAIS | F129: 0 | G129: FGE0107 | H129: GECTB | I129: SUPOC | J129: DICOR
A130: F333206000 | B130: PROTEÇÃO E PRIVACIDADE DE DADOS | C130: GERÊNCIA DE CONSULTORIAS | D130: SUPERINTENDÊNCIA JURÍDICA | E130: DIRETORIA JURÍDICA | F130: Outras | G130: FGE0102 | H130: GECST | I130: SEJUR | J130: DIJUR
A131: F333204000 | B131: ESCRITÓRIO DE PROJETOS | C131: ESCRITÓRIO DE PROJETOS | D131: DIRETORIA TÉCNICA, DE ESTUDOS E DE RELAÇÕES REGULATÓRIAS | E131: DIRETORIA TÉCNICA, DE ESTUDOS E DE RELAÇÕES REGULATÓRIAS | F131: 0 | G131: ESCRPRJ | H131: ESCRPRJ | I131: DITEC | J131: DITEC
A132: F333400000 | B132: SUPERINTENDÊNCIA DE RECURSOS HUMANOS | C132: SUPERINTENDÊNCIA DE RECURSOS HUMANOS | D132: SUPERINTENDÊNCIA DE RECURSOS HUMANOS | E132: DIRETORIA DE ASSUNTOS CORPORATIVOS E RELAÇÕES SINDICAIS | F132: 0 | G132: FSU0119 | H132: SUPRH | I132: SUPRH | J132: DICOR
A133: F333401000 | B133: GERÊNCIA DE RECURSOS HUMANOS | C133: GERÊNCIA DE RECURSOS HUMANOS | D133: SUPERINTENDÊNCIA DE RECURSOS HUMANOS | E133: DIRETORIA DE ASSUNTOS CORPORATIVOS E RELAÇÕES SINDICAIS | F133: 0 | G133: FGE0133 | H133: GERRH | I133: SUPRH | J133: DICOR
A134: F333500000 | B134: SUPER. DE RELAC. COM PODER EXECUTIVO | C134: SUPERINTENDÊNCIA DE RELACIONAMENTO COM PODER EXECUTIVO | D134: SUPERINTENDÊNCIA DE RELACIONAMENTO COM PODER EXECUTIVO | E134: DIRETORIA DE RELAÇÕES INSTITUCIONAIS | F134: 0 | G134: FSU0202 | H134: SUPEX | I134: SUPEX | J134: DIRIN
A135: F601000001 | B135: INSTITUCIONAL - SAÚDE | C135: INSTITUCIONAL FEDERAÇÕES | D135: INSTITUCIONAL FEDERAÇÕES | E135: INSTITUCIONAL FEDERAÇÕES | F135: 0 | H135: INSFED | I135: INSFED | J135: INSFED
A136: F602000001 | B136: INSTITUCIONAL - SEGUROS GERAIS | C136: INSTITUCIONAL FEDERAÇÕES | D136: INSTITUCIONAL FEDERAÇÕES | E136: INSTITUCIONAL FEDERAÇÕES | F136: 0 | H136: INSFED | I136: INSFED | J136: INSFED
A137: F603000001 | B137: INSTITUCIONAL - PREVIDÊNCIA PRIVADA | C137: INSTITUCIONAL FEDERAÇÕES | D137: INSTITUCIONAL FEDERAÇÕES | E137: INSTITUCIONAL FEDERAÇÕES | F137: 0 | H137: INSFED | I137: INSFED | J137: INSFED
A138: F604000001 | B138: INSTITUCIONAL - CAPITALIZAÇÃO | C138: INSTITUCIONAL FEDERAÇÕES | D138: INSTITUCIONAL FEDERAÇÕES | E138: INSTITUCIONAL FEDERAÇÕES | F138: 0 | H138: INSFED | I138: INSFED | J138: INSFED
A139: F605000001 | B139: INSTITUCIONAL - SINDICATO | C139: INSTITUCIONAL - SINDICATO | D139: INSTITUCIONAL - SINDICATO | E139: INSTITUCIONAL FEDERAÇÕES | F139: 0 | H139: INSID | I139: INSID | J139: INSID
A140: F333205000 | B140: AJUSTES ORÇAMENTO | C140: GERÊNCIA DE ATENDIMENTO | D140: DIRETORIA DE SERVIÇOS AS ASSOCIADAS | E140: DIRETORIA DE SERVIÇOS AS ASSOCIADAS | F140: SISEG
A142: CNSEG
A143: Centro de Custo | B143: Descrição MXM | C143: Gerência | D143: Superintendência | E143: Diretoria | F143: Classificação BP e DRE
A144: N010000000 | B144: PRESIDENCIA | C144: PRESIDENCIA | D144: PRESIDENCIA | E144: PRESIDENCIA | G144: NPR0001 | H144: PRESI | I144: PRESI | J144: PRESI
A145: N010101000 | B145: RECEITAS | C145: DIRETORIA ADMINISTRATIVA | D145: DIRETORIA ADMINISTRATIVA | E145: DIRETORIA ADMINISTRATIVA
A146: N010101001 | B146: DESPESAS CNSEG | C146: DIRETORIA ADMINISTRATIVA | D146: DIRETORIA ADMINISTRATIVA | E146: DIRETORIA ADMINISTRATIVA
A147: N020000000 | B147: DIRETORIA DE SERVIÇOS ÀS ASSOCIADAS | C147: DIRETORIA DE SERVIÇOS AS ASSOCIADAS | D147: DIRETORIA DE SERVIÇOS AS ASSOCIADAS | E147: DIRETORIA DE SERVIÇOS AS ASSOCIADAS | G147: NDX0101 | H147: DISERV | I147: DISERV | J147: DISERV
A148: N020100000 | B148: SUPERINTENDÊNCIA | C148: SUPERINTENDENCIA DE SERVIÇOS AS ASSOCIADAS | D148: SUPERINTENDÊNCIA DE SERVIÇOS AS ASSOCIADAS | E148: DIRETORIA DE SERVIÇOS AS ASSOCIADAS
A149: N020101000 | B149: GERÊNCIA DE OPERAÇÕES E PRODUTOS | C149: GERÊNCIA DE OPERAÇÕES E PRODUTOS | D149: DIRETORIA DE SERVIÇOS AS ASSOCIADAS | E149: DIRETORIA DE SERVIÇOS AS ASSOCIADAS | F149: SISEG | G149: NGE0101 | H149: DISERV | I149: DISERV | J149: DISERV
A150: N020101001 | B150: RENAVAM BIN FABRIL | C150: GERÊNCIA DE OPERAÇÕES E PRODUTOS | D150: DIRETORIA DE SERVIÇOS AS ASSOCIADAS | E150: DIRETORIA DE SERVIÇOS AS ASSOCIADAS | F150: SISEG | G150: NGE0101 | H150: DISERV | I150: DISERV | J150: DISERV
A151: N020101002 | B151: RENAVAM BIN ESTADUAL | C151: GERÊNCIA DE OPERAÇÕES E PRODUTOS | D151: DIRETORIA DE SERVIÇOS AS ASSOCIADAS | E151: DIRETORIA DE SERVIÇOS AS ASSOCIADAS | F151: SISEG | G151: NGE0101 | H151: DISERV | I151: DISERV | J151: DISERV
A152: N020101003 | B152: ENQUADRAMENTO DE VEÍCULOS | C152: GERÊNCIA DE OPERAÇÕES E PRODUTOS | D152: DIRETORIA DE SERVIÇOS AS ASSOCIADAS | E152: DIRETORIA DE SERVIÇOS AS ASSOCIADAS | F152: SISEG | G152: NGE0101 | H152: DISERV | I152: DISERV | J152: DISERV
A153: N020101004 | B153: MONITORAMENTO RF | C153: GERÊNCIA DE OPERAÇÕES E PRODUTOS | D153: DIRETORIA DE SERVIÇOS AS ASSOCIADAS | E153: DIRETORIA DE SERVIÇOS AS ASSOCIADAS | F153: SISEG | G153: NGE0101 | H153: DISERV | I153: DISERV | J153: DISERV
A154: N020101005 | B154: BDV | C154: GERÊNCIA DE OPERAÇÕES E PRODUTOS | D154: DIRETORIA DE SERVIÇOS AS ASSOCIADAS | E154: DIRETORIA DE SERVIÇOS AS ASSOCIADAS | F154: SISEG | G154: NGE0101 | H154: DISERV | I154: DISERV | J154: DISERV
A155: N020101006 | B155: DASHBOARD DE SEGUROS AUTO | C155: GERÊNCIA DE OPERAÇÕES E PRODUTOS | D155: DIRETORIA DE SERVIÇOS AS ASSOCIADAS | E155: DIRETORIA DE SERVIÇOS AS ASSOCIADAS | F155: SISEG | G155: NGE0101 | H155: DISERV | I155: DISERV | J155: DISERV
A156: N020101007 | B156: RENAVAM BIN RF | C156: GERÊNCIA DE OPERAÇÕES E PRODUTOS | D156: DIRETORIA DE SERVIÇOS AS ASSOCIADAS | E156: DIRETORIA DE SERVIÇOS AS ASSOCIADAS | F156: SISEG | G156: NGE0101 | H156: DISERV | I156: DISERV | J156: DISERV
A157: N020101008 | B157: SIVVE | C157: GERÊNCIA DE OPERAÇÕES E PRODUTOS | D157: DIRETORIA DE SERVIÇOS AS ASSOCIADAS | E157: DIRETORIA DE SERVIÇOS AS ASSOCIADAS | F157: SISEG | G157: NGE0101 | H157: DISERV | I157: DISERV | J157: DISERV
A158: N020101009 | B158: RENACH | C158: GERÊNCIA DE OPERAÇÕES E PRODUTOS | D158: DIRETORIA DE SERVIÇOS AS ASSOCIADAS | E158: DIRETORIA DE SERVIÇOS AS ASSOCIADAS | F158: SISEG | G158: NGE0101 | H158: DISERV | I158: DISERV | J158: DISERV
A159: N020101010 | B159: ARQUIVO ESPECIAL - RNS AUTO | C159: GERÊNCIA DE OPERAÇÕES E PRODUTOS | D159: DIRETORIA DE SERVIÇOS AS ASSOCIADAS | E159: DIRETORIA DE SERVIÇOS AS ASSOCIADAS | F159: SISEG | G159: NGE0101 | H159: DISERV | I159: DISERV | J159: DISERV
A160: N020101011 | B160: RNS AUTO | C160: GERÊNCIA DE OPERAÇÕES E PRODUTOS | D160: DIRETORIA DE SERVIÇOS AS ASSOCIADAS | E160: DIRETORIA DE SERVIÇOS AS ASSOCIADAS | F160: SISEG | G160: NGE0101 | H160: DISERV | I160: DISERV | J160: DISERV
... A166: N020101017 | B166: SCCP | C166: GERÊNCIA DE OPERAÇÕES E PRODUTOS | D166: DIRETORIA DE SERVIÇOS AS ASSOCIADAS | E166: DIRETORIA DE SERVIÇOS AS ASSOCIADAS | F166: SISEG | G166: NGE0101 | H166: DISERV | I166: DISERV | J166: DISERV
A167: N020102000 | B167: GERÊNCIA DE TI | C167: GERÊNCIA DE TI | D167: DIRETORIA DE SERVIÇOS AS ASSOCIADAS | E167: DIRETORIA DE SERVIÇOS AS ASSOCIADAS | H167: GERTI | I167: DISERV | J167: DISERV
A168: N020103000 | B168: GERÊNCIA COMERCIAL | C168: GERÊNCIA COMERCIAL | D168: DIRETORIA DE SERVIÇOS AS ASSOCIADAS | E168: DIRETORIA DE SERVIÇOS AS ASSOCIADAS | H168: GERCOM | I168: DISERV | J168: DISERV
A169: N020104000 | B169: GERÊNCIA DE MARKETING COMERCIAL | C169: GERÊNCIA DE MARKETING COMERCIAL | D169: DIRETORIA DE SERVIÇOS AS ASSOCIADAS | E169: DIRETORIA DE SERVIÇOS AS ASSOCIADAS | H169: GMKTCO | I169: DISERV | J169: DISERV
...

Sheet Fluxo de caixa
A1: Classificação das contas do fluxo de caixa
A3: Descrição | B3: Grupo Relatório | C3: Revisão Analítica | D3: Notas
A4: Receita de Inscrições | B4: Receita operacional líquida | C4: Outras receitas | D4: Eventos
A5: Aluguel | B5: Receita operacional líquida | C5: Outras receitas | D5: Receita de aluguéis
A6: Contribuição Assistencial | B6: Receita operacional líquida | C6: Outras receitas | D6: Contribuição sindical
A7: Outros (Recto Duplicidade, des | B7: Receita operacional líquida | C7: Outras receitas | D7: Outras receitas
A8: Receita de Patrocinios | B8: Receita operacional líquida | C8: Outras receitas | D8: Eventos
A9: Recuperação Despesas - Outras | B9: Receita operacional líquida | C9: Outras receitas | D9: Outras receitas
A10: Rendimento CDB | B10: Receitas financeiras | C10: Receitas de aplicações financeiras | D10: Receitas de aplicações financeiras
A11: Rendimento Fundos | B11: Receitas financeiras | C11: Receitas de aplicações financeiras | D11: Receitas de aplicações financeiras
A12: Rendimento Outras Aplicações | B12: Receitas financeiras | C12: Receitas de aplicações financeiras | D12: Receitas de aplicações financeiras
A13: SIRCOF | B13: Receita operacional líquida | C13: Sistema de contratos | D13: Sistema de Contratos (Ex-Sircof)
A14: SISEG | B14: Receita operacional líquida | C14: Sistema de contratos | D14: SISEG
... A148: IOF sobre invest financeiros | B148: Despesas financeiras | C148: Outras despesas financeiras | D148: Outras despesas financeiras
